{"itemInfo": {"itemStruct": {"id": "7297873309109144839", "desc": "\u0e2b\u0e25\u0e27\u0e07\u0e1e\u0e23\u0e30\u0e1a\u0e32\u0e07\u200b\u0e2a\u0e2d\u0e07\u0e27\u0e31\u0e19\u0e2b\u0e19\u0e36\u0e48\u0e07\u200b\u0e04\u0e37\u0e19\u200b  ep2 #\u0e2b\u0e25\u0e27\u0e07\u0e1e\u0e23\u0e30\u0e1a\u0e32\u0e07\u0e40\u0e21\u0e37\u0e2d\u0e07\u0e21\u0e23\u0e14\u0e01\u0e42\u0e25\u0e01 #\u0e2d\u0e32\u0e2b\u0e32\u0e23\u0e1a\u0e49\u0e32\u0e19\u0e46 #jubulin ", "createTime": "1699168546", "scheduleTime": 0, "video": {"id": "7297873309109144839", "height": 0, "width": 0, "duration": 0, "ratio": "", "cover": "https://p16-common-sign.tiktokcdn-us.com/tos-alisg-i-photomode-sg/6fd5a54c94b740109e0344c05d44ec5b~tplv-photomode-image.jpeg?dr=9616&x-expires=1771110000&x-signature=dIgQYU5Duvxl8BmhHcyxfeKRUG0%3D&t=4d5b0474&ps=13740610&shp=81f88b70&shcp=9b759fb9&idc=useast5&ftpl=1", "originCover": "https://p16-common-sign.tiktokcdn-us.com/tos-alisg-i-photomode-sg/6fd5a54c94b740109e0344c05d44ec5b~tplv-photomode-image.jpeg?dr=9616&x-expires=1771110000&x-signature=dIgQYU5Duvxl8BmhHcyxfeKRUG0%3D&t=4d5b0474&ps=13740610&shp=81f88b70&shcp=9b759fb9&idc=useast5&ftpl=1", "dynamicCover": "", "playAddr": "", "downloadAddr": "", "shareCover": [""], "reflowCover": "", "zoomCover": {"240": "", "480": "", "720": "", "960": ""}}, "author": {"id": "6812154143386829825", "shortId": "", "uniqueId": "jubukhamphay", "nickname": "Jubulin", "avatarLarger": "https://p19-common-sign.tiktokcdn-us.com/tos-alisg-avt-0068/f008714a85dc8d52ad6fc07f4a338944~tplv-tiktokx-cropcenter:1080:1080.jpeg?dr=9640&refresh_token=9c7a4c9c&x-expires=1771110000&x-signature=tnUDFLp391A1c%2BQ0R5vkqznYjqk%3D&t=4d5b0474&ps=13740610&shp=a5d48078&shcp=81f88b70&idc=useast5", "avatarMedium": "https://p19-common-sign.tiktokcdn-us.com/tos-alisg-avt-0068/f008714a85dc8d52ad6fc07f4a338944~tplv-tiktokx-cropcenter:720:720.jpeg?dr=9640&refresh_token=08907cb2&x-expires=1771110000&x-signature=cH0UnA8%2BK9dinxMeA5SrZOK%2FOrs%3D&t=4d5b0474&ps=13740610&shp=a5d48078&shcp=81f88b70&idc=useast5", "avatarThumb": "https://p16-common-sign.tiktokcdn-us.com/tos-alisg-avt-0068/f008714a85dc8d52ad6fc07f4a338944~tplv-tiktokx-cropcenter:100:100.jpeg?dr=9640&refresh_token=67ffbfb3&x-expires=1771110000&x-signature=ogNmpYtN1WrLrAhb4%2F0o23rp0oc%3D&t=4d5b0474&ps=13740610&shp=a5d48078&shcp=81f88b70&idc=useast5", "signature": "\u0e44\u0e21\u0e48\u0e21\u0e35\u0e2a\u0e32\u0e23\u0e30", "createTime": 1683248858, "verified": false, "secUid": "MS4wLjABAAAAQFUyomz8xb5kUJvGlN2uaZ3Q7e3Xigcsrc_KOt1vn0onIbMHJZb4F4uyPno00rCY", "ftc": false, "relation": 0, "openFavorite": true, "commentSetting": 0, "duetSetting": 0, "stitchSetting": 0, "privateAccount": false, "secret": false, "isADVirtual": false, "roomId": "", "uniqueIdModifyTime": 0, "ttSeller": false, "downloadSetting": 0, "recommendReason": "", "nowInvitationCardUrl": "", "nickNameModifyTime": 0, "isEmbedBanned": false, "canExpPlaylist": false, "suggestAccountBind": false, "UserStoryStatus": 0}, "music": {"id": "7179600429985073153", "title": "No Reason", "playUrl": "https://sf16.tiktokcdn-us.com/obj/tos-alisg-ve-2774/oQtZnDg4Q9jdCztfoBG81Q8qLoeJIBbx7ZCIFo", "coverLarge": "https://p16-common.tiktokcdn-us.com/tos-alisg-v-2774/8f3770d8da9b457bbe97cf23eefadac8~tplv-tiktokx-cropcenter:720:720.jpeg?dr=9584&t=4d5b0474&ps=933b5bde&shp=08d74b56&shcp=81f88b70&idc=useast5", "coverMedium": "https://p16-common.tiktokcdn-us.com/tos-alisg-v-2774/8f3770d8da9b457bbe97cf23eefadac8~tplv-tiktokx-cropcenter:200:200.jpeg?dr=9584&t=4d5b0474&ps=933b5bde&shp=08d74b56&shcp=81f88b70&idc=useast5", "coverThumb": "https://p16-common.tiktokcdn-us.com/tos-alisg-v-2774/8f3770d8da9b457bbe97cf23eefadac8~tplv-tiktokx-cropcenter:100:100.jpeg?dr=9584&t=4d5b0474&ps=933b5bde&shp=08d74b56&shcp=81f88b70&idc=useast5", "authorName": "Ryan.B", "original": false, "private": false, "duration": 60, "album": "No Reason", "scheduleSearchTime": 0, "collected": false, "preciseDuration": {"preciseDuration": 60, "preciseShootDuration": 60, "preciseAuditionDuration": 60, "preciseVideoDuration": 6000}, "isCopyrighted": false, "tt2dsp": {"tt_to_dsp_song_infos": [{"ShowStrategy": "1", "Platform": 1, "SongId": "1374966842", "Token": {"AppleMusicToken": {"DeveloperToken": "eyJhbGciOiJFUzI1NiIsImtpZCI6Ikc2Q0dLMjdWQzMifQ.eyJleHAiOjE3NzExMDg0OTAsImlhdCI6MTc3MDg0OTI5MCwiaXNzIjoiTUo3OTdEOFU2RiJ9.2oBJtuITtYo2sEkYrzBl4vn6jktVCu6T4Jgn25ChqGxKfwt6MeIsWKiV3dUumwL5mfiCAzfyQNL0iAXN5Vt0og"}}, "MetaSongId": "7179600427753670657"}, {"ShowStrategy": "1", "Platform": 3, "SongId": "7uwJwSKpmzZH7p7imm4f1P", "MetaSongId": "7179600427753670657"}]}, "is_unlimited_music": false, "is_commerce_music": false, "shoot_duration": 60}, "challenges": [{"id": "1680077585051650", "title": "\u0e2b\u0e25\u0e27\u0e07\u0e1e\u0e23\u0e30\u0e1a\u0e32\u0e07\u0e40\u0e21\u0e37\u0e2d\u0e07\u0e21\u0e23\u0e14\u0e01\u0e42\u0e25\u0e01", "desc": "", "profileLarger": "", "profileMedium": "", "profileThumb": "", "coverLarger": "", "coverMedium": "", "coverThumb": ""}, {"id": "1601796731667458", "title": "\u0e2d\u0e32\u0e2b\u0e32\u0e23\u0e1a\u0e49\u0e32\u0e19\u0e46", "desc": "", "profileLarger": "", "profileMedium": "", "profileThumb": "", "coverLarger": "", "coverMedium": "", "coverThumb": ""}, {"id": "1704653037601801", "title": "jubulin", "desc": "", "profileLarger": "", "profileMedium": "", "profileThumb": "", "coverLarger": "", "coverMedium": "", "coverThumb": ""}], "stats": {"diggCount": 10, "shareCount": 0, "commentCount": 0, "playCount": 140, "collectCount": "0"}, "statsV2": {"diggCount": "10", "shareCount": "0", "commentCount": "0", "playCount": "140", "collectCount": "0", "repostCount": "0"}, "warnInfo": [], "originalItem": false, "officalItem": false, "textExtra": [{"awemeId": "", "start": 33, "end": 56, "hashtagId": "1680077585051650", "hashtagName": "\u0e2b\u0e25\u0e27\u0e07\u0e1e\u0e23\u0e30\u0e1a\u0e32\u0e07\u0e40\u0e21\u0e37\u0e2d\u0e07\u0e21\u0e23\u0e14\u0e01\u0e42\u0e25\u0e01", "type": 1, "subType": 0, "isCommerce": false}, {"awemeId": "", "start": 57, "end": 68, "hashtagId": "1601796731667458", "hashtagName": "\u0e2d\u0e32\u0e2b\u0e32\u0e23\u0e1a\u0e49\u0e32\u0e19\u0e46", "type": 1, "subType": 0, "isCommerce": false}, {"awemeId": "", "start": 69, "end": 77, "hashtagId": "1704653037601801", "hashtagName": "jubulin", "type": 1, "subType": 0, "isCommerce": false}], "secret": false, "forFriend": false, "digged": false, "itemCommentStatus": 0, "takeDown": 0, "effectStickers": [], "authorStats": {"followerCount": 88, "followingCount": 229, "heart": 728, "heartCount": 728, "videoCount": 82, "diggCount": 603, "friendCount": 0}, "privateItem": false, "stickersOnItem": [], "isAd": false, "shareEnabled": true, "comments": [], "duetDisplay": 0, "stitchDisplay": 0, "indexEnabled": true, "imagePost": {"images": [{"imageURL": {"urlList": ["https://p19-common-sign.tiktokcdn-us.com/tos-alisg-i-photomode-sg/6fd5a54c94b740109e0344c05d44ec5b~tplv-photomode-image.jpeg?dr=9616&x-expires=1771110000&x-signature=YhqsBQSJKqS9ToQKt0iR0NJXmQI%3D&t=4d5b0474&ps=13740610&shp=81f88b70&shcp=9b759fb9&idc=useast5&ftpl=1", "https://p16-common-sign.tiktokcdn-us.com/tos-alisg-i-photomode-sg/6fd5a54c94b740109e0344c05d44ec5b~tplv-photomode-image.jpeg?dr=9616&x-expires=1771110000&x-signature=dIgQYU5Duvxl8BmhHcyxfeKRUG0%3D&t=4d5b0474&ps=13740610&shp=81f88b70&shcp=9b759fb9&idc=useast5&ftpl=1"]}, "imageWidth": 2304, "imageHeight": 3072}, {"imageURL": {"urlList": ["https://p16-common-sign.tiktokcdn-us.com/tos-alisg-i-photomode-sg/a7332454d9f647e0bc88bb78910f27a6~tplv-photomode-image.jpeg?dr=9616&x-expires=1771110000&x-signature=Ucdj%2F7ntPGNiM27jOW%2Bm73qjq%2Fw%3D&t=4d5b0474&ps=13740610&shp=81f88b70&shcp=9b759fb9&idc=useast5&ftpl=1", "https://p19-common-sign.tiktokcdn-us.com/tos-alisg-i-photomode-sg/a7332454d9f647e0bc88bb78910f27a6~tplv-photomode-image.jpeg?dr=9616&x-expires=1771110000&x-signature=CF41TSueIb0PU1dmNG6tfae9A9I%3D&t=4d5b0474&ps=13740610&shp=81f88b70&shcp=9b759fb9&idc=useast5&ftpl=1"]}, "imageWidth": 2112, "imageHeight": 2816}, {"imageURL": {"urlList": ["https://p16-common-sign.tiktokcdn-us.com/tos-alisg-i-photomode-sg/7bd9cce9c3c647369b133884660a9343~tplv-photomode-image.jpeg?dr=9616&x-expires=1771110000&x-signature=g2Ewk%2BAOjLrpRTImtPFQmWt6xxo%3D&t=4d5b0474&ps=13740610&shp=81f88b70&shcp=9b759fb9&idc=useast5&ftpl=1", "https://p19-common-sign.tiktokcdn-us.com/tos-alisg-i-photomode-sg/7bd9cce9c3c647369b133884660a9343~tplv-photomode-image.jpeg?dr=9616&x-expires=1771110000&x-signature=djFFIWX5m63ojwlJq1JxsksIaQc%3D&t=4d5b0474&ps=13740610&shp=81f88b70&shcp=9b759fb9&idc=useast5&ftpl=1"]}, "imageWidth": 2304, "imageHeight": 3072}, {"imageURL": {"urlList": ["https://p16-common-sign.tiktokcdn-us.com/tos-alisg-i-photomode-sg/320bae03d17d465ebc999f21cb900b77~tplv-photomode-image.jpeg?dr=9616&x-expires=1771110000&x-signature=evJu1wTDycUf1fB%2BNQWNlADw1ho%3D&t=4d5b0474&ps=13740610&shp=81f88b70&shcp=9b759fb9&idc=useast5&ftpl=1", "https://p19-common-sign.tiktokcdn-us.com/tos-alisg-i-photomode-sg/320bae03d17d465ebc999f21cb900b77~tplv-photomode-image.jpeg?dr=9616&x-expires=1771110000&x-signature=3lFzkrmrT5glWJ6hVDCOXzscvx8%3D&t=4d5b0474&ps=13740610&shp=81f88b70&shcp=9b759fb9&idc=useast5&ftpl=1"]}, "imageWidth": 1200, "imageHeight": 1600}, {"imageURL": {"urlList": ["https://p16-common-sign.tiktokcdn-us.com/tos-alisg-i-photomode-sg/642392772bc54a4daf26ab069ecf7636~tplv-photomode-image.jpeg?dr=9616&x-expires=1771110000&x-signature=6HpFmkaEldrS5IgjeBsuoOjKDPU%3D&t=4d5b0474&ps=13740610&shp=81f88b70&shcp=9b759fb9&idc=useast5&ftpl=1", "https://p19-common-sign.tiktokcdn-us.com/tos-alisg-i-photomode-sg/642392772bc54a4daf26ab069ecf7636~tplv-photomode-image.jpeg?dr=9616&x-expires=1771110000&x-signature=SoXB%2FWQieu7DToLBv4BheAiJD1w%3D&t=4d5b0474&ps=13740610&shp=81f88b70&shcp=9b759fb9&idc=useast5&ftpl=1"]}, "imageWidth": 1200, "imageHeight": 1600}, {"imageURL": {"urlList": ["https://p16-common-sign.tiktokcdn-us.com/tos-alisg-i-photomode-sg/6205f40eda3742e1bbe02862cee9b885~tplv-photomode-image.jpeg?dr=9616&x-expires=1771110000&x-signature=4zuNxnEb8mXVGFcZIh1vRm6DRjI%3D&t=4d5b0474&ps=13740610&shp=81f88b70&shcp=9b759fb9&idc=useast5&ftpl=1", "https://p19-common-sign.tiktokcdn-us.com/tos-alisg-i-photomode-sg/6205f40eda3742e1bbe02862cee9b885~tplv-photomode-image.jpeg?dr=9616&x-expires=1771110000&x-signature=fCmqxhEGSjya9S1k4w0XwOxTS4M%3D&t=4d5b0474&ps=13740610&shp=81f88b70&shcp=9b759fb9&idc=useast5&ftpl=1"]}, "imageWidth": 2304, "imageHeight": 3072}, {"imageURL": {"urlList": ["https://p16-common-sign.tiktokcdn-us.com/tos-alisg-i-photomode-sg/a7a543a9c1d54f049506cd2321bf6be8~tplv-photomode-image.jpeg?dr=9616&x-expires=1771110000&x-signature=jVVeQ9iAF93r1k9M4OOCXZ5ykfs%3D&t=4d5b0474&ps=13740610&shp=81f88b70&shcp=9b759fb9&idc=useast5&ftpl=1", "https://p19-common-sign.tiktokcdn-us.com/tos-alisg-i-photomode-sg/a7a543a9c1d54f049506cd2321bf6be8~tplv-photomode-image.jpeg?dr=9616&x-expires=1771110000&x-signature=BmgnnyEnUX%2FpCENmR4kQg%2Fi6%2Bf8%3D&t=4d5b0474&ps=13740610&shp=81f88b70&shcp=9b759fb9&idc=useast5&ftpl=1"]}, "imageWidth": 2304, "imageHeight": 3072}, {"imageURL": {"urlList": ["https://p16-common-sign.tiktokcdn-us.com/tos-alisg-i-photomode-sg/584e966ae7d44910a8abf1cf0cfb7beb~tplv-photomode-image.jpeg?dr=9616&x-expires=1771110000&x-signature=ZJcOjtaq1UHXdglHkz6pkMpgkfs%3D&t=4d5b0474&ps=13740610&shp=81f88b70&shcp=9b759fb9&idc=useast5&ftpl=1", "https://p19-common-sign.tiktokcdn-us.com/tos-alisg-i-photomode-sg/584e966ae7d44910a8abf1cf0cfb7beb~tplv-photomode-image.jpeg?dr=9616&x-expires=1771110000&x-signature=jUehjeYQknUddfik8ftn2rZ23w0%3D&t=4d5b0474&ps=13740610&shp=81f88b70&shcp=9b759fb9&idc=useast5&ftpl=1"]}, "imageWidth": 2304, "imageHeight": 3072}, {"imageURL": {"urlList": ["https://p16-common-sign.tiktokcdn-us.com/tos-alisg-i-photomode-sg/3271178dbcae4671bfe04e1ab6c3c3c9~tplv-photomode-image.jpeg?dr=9616&x-expires=1771110000&x-signature=VlNIaf7kAnzWfwdX%2B7GH3onF2qQ%3D&t=4d5b0474&ps=13740610&shp=81f88b70&shcp=9b759fb9&idc=useast5&ftpl=1", "https://p19-common-sign.tiktokcdn-us.com/tos-alisg-i-photomode-sg/3271178dbcae4671bfe04e1ab6c3c3c9~tplv-photomode-image.jpeg?dr=9616&x-expires=1771110000&x-signature=7OXON6tKNohQr27aRCBcB%2FB74YY%3D&t=4d5b0474&ps=13740610&shp=81f88b70&shcp=9b759fb9&idc=useast5&ftpl=1"]}, "imageWidth": 2304, "imageHeight": 3072}, {"imageURL": {"urlList": ["https://p19-common-sign.tiktokcdn-us.com/tos-alisg-i-photomode-sg/f866367b087f4b8cb2c9188f30a1894f~tplv-photomode-image.jpeg?dr=9616&x-expires=1771110000&x-signature=FPKu%2FvGdDKjvfz%2FXgdyNMbb%2BjFM%3D&t=4d5b0474&ps=13740610&shp=81f88b70&shcp=9b759fb9&idc=useast5&ftpl=1", "https://p16-common-sign.tiktokcdn-us.com/tos-alisg-i-photomode-sg/f866367b087f4b8cb2c9188f30a1894f~tplv-photomode-image.jpeg?dr=9616&x-expires=1771110000&x-signature=KvIi6Prce87z3Lvjc1fzxqWhvOk%3D&t=4d5b0474&ps=13740610&shp=81f88b70&shcp=9b759fb9&idc=useast5&ftpl=1"]}, "imageWidth": 2304, "imageHeight": 3072}, {"imageURL": {"urlList": ["https://p19-common-sign.tiktokcdn-us.com/tos-alisg-i-photomode-sg/31f6664d8f0b4601a95bc86cacbf748b~tplv-photomode-image.jpeg?dr=9616&x-expires=1771110000&x-signature=me7QrVmfdK36n8%2Fnf5WNwTlkzu8%3D&t=4d5b0474&ps=13740610&shp=81f88b70&shcp=9b759fb9&idc=useast5&ftpl=1", "https://p16-common-sign.tiktokcdn-us.com/tos-alisg-i-photomode-sg/31f6664d8f0b4601a95bc86cacbf748b~tplv-photomode-image.jpeg?dr=9616&x-expires=1771110000&x-signature=PqXDTW5htYe5RqsNLl0MMiIlqUY%3D&t=4d5b0474&ps=13740610&shp=81f88b70&shcp=9b759fb9&idc=useast5&ftpl=1"]}, "imageWidth": 2304, "imageHeight": 3072}, {"imageURL": {"urlList": ["https://p16-common-sign.tiktokcdn-us.com/tos-alisg-i-photomode-sg/044efeceab4f4a629c7deb38665961b0~tplv-photomode-image.jpeg?dr=9616&x-expires=1771110000&x-signature=sewhMdy%2FvGRZLT1yR87DCgjrcKM%3D&t=4d5b0474&ps=13740610&shp=81f88b70&shcp=9b759fb9&idc=useast5&ftpl=1", "https://p19-common-sign.tiktokcdn-us.com/tos-alisg-i-photomode-sg/044efeceab4f4a629c7deb38665961b0~tplv-photomode-image.jpeg?dr=9616&x-expires=1771110000&x-signature=yKzO9wNnDs6HI13Ur3H%2FR9I3484%3D&t=4d5b0474&ps=13740610&shp=81f88b70&shcp=9b759fb9&idc=useast5&ftpl=1"]}, "imageWidth": 2304, "imageHeight": 3072}, {"imageURL": {"urlList": ["https://p16-common-sign.tiktokcdn-us.com/tos-alisg-i-photomode-sg/03f8922406cb470fb09d00db30b6124b~tplv-photomode-image.jpeg?dr=9616&x-expires=1771110000&x-signature=VOIRI3VXyapZ%2BJYtv8FrHgFdrdQ%3D&t=4d5b0474&ps=13740610&shp=81f88b70&shcp=9b759fb9&idc=useast5&ftpl=1", "https://p19-common-sign.tiktokcdn-us.com/tos-alisg-i-photomode-sg/03f8922406cb470fb09d00db30b6124b~tplv-photomode-image.jpeg?dr=9616&x-expires=1771110000&x-signature=YPY33eAmggDZ%2BaPNG7Wbnr2tYEM%3D&t=4d5b0474&ps=13740610&shp=81f88b70&shcp=9b759fb9&idc=useast5&ftpl=1"]}, "imageWidth": 1200, "imageHeight": 1600}, {"imageURL": {"urlList": ["https://p19-common-sign.tiktokcdn-us.com/tos-alisg-i-photomode-sg/5c4e0e9ce4a84afc85c377cd85e6a296~tplv-photomode-image.jpeg?dr=9616&x-expires=1771110000&x-signature=cAO4HT8FnZq0OhGkNtc9gU3w44I%3D&t=4d5b0474&ps=13740610&shp=81f88b70&shcp=9b759fb9&idc=useast5&ftpl=1", "https://p16-common-sign.tiktokcdn-us.com/tos-alisg-i-photomode-sg/5c4e0e9ce4a84afc85c377cd85e6a296~tplv-photomode-image.jpeg?dr=9616&x-expires=1771110000&x-signature=ZcYYXnk%2FISCv0hsXUo1MTazoTKs%3D&t=4d5b0474&ps=13740610&shp=81f88b70&shcp=9b759fb9&idc=useast5&ftpl=1"]}, "imageWidth": 1200, "imageHeight": 1600}, {"imageURL": {"urlList": ["https://p16-common-sign.tiktokcdn-us.com/tos-alisg-i-photomode-sg/5551c9b4e35b494aa30f1cf051281063~tplv-photomode-image.jpeg?dr=9616&x-expires=1771110000&x-signature=Rk11cwRsauI6rHwHhoY7u8ihnA4%3D&t=4d5b0474&ps=13740610&shp=81f88b70&shcp=9b759fb9&idc=useast5&ftpl=1", "https://p19-common-sign.tiktokcdn-us.com/tos-alisg-i-photomode-sg/5551c9b4e35b494aa30f1cf051281063~tplv-photomode-image.jpeg?dr=9616&x-expires=1771110000&x-signature=t7kUE8ZGO0zxfLmMAJAtPlKqhT0%3D&t=4d5b0474&ps=13740610&shp=81f88b70&shcp=9b759fb9&idc=useast5&ftpl=1"]}, "imageWidth": 1200, "imageHeight": 1600}, {"imageURL": {"urlList": ["https://p16-common-sign.tiktokcdn-us.com/tos-alisg-i-photomode-sg/e18b6ee5e00d47b08211047c2a5562ac~tplv-photomode-image.jpeg?dr=9616&x-expires=1771110000&x-signature=mIRfTFK%2Fahnct4BBhthgHsTdHM0%3D&t=4d5b0474&ps=13740610&shp=81f88b70&shcp=9b759fb9&idc=useast5&ftpl=1", "https://p19-common-sign.tiktokcdn-us.com/tos-alisg-i-photomode-sg/e18b6ee5e00d47b08211047c2a5562ac~tplv-photomode-image.jpeg?dr=9616&x-expires=1771110000&x-signature=zIFAPx%2B6WqjkX8J0nz1ozR0XSBE%3D&t=4d5b0474&ps=13740610&shp=81f88b70&shcp=9b759fb9&idc=useast5&ftpl=1"]}, "imageWidth": 1200, "imageHeight": 1600}, {"imageURL": {"urlList": ["https://p16-common-sign.tiktokcdn-us.com/tos-alisg-i-photomode-sg/76c5b018d7274cd5af1af5962a98e9b9~tplv-photomode-image.jpeg?dr=9616&x-expires=1771110000&x-signature=IWzCIEDHlAX%2BWU64UWn5hAcsquo%3D&t=4d5b0474&ps=13740610&shp=81f88b70&shcp=9b759fb9&idc=useast5&ftpl=1", "https://p19-common-sign.tiktokcdn-us.com/tos-alisg-i-photomode-sg/76c5b018d7274cd5af1af5962a98e9b9~tplv-photomode-image.jpeg?dr=9616&x-expires=1771110000&x-signature=xQkVd1W%2BALqgbS8rvTys2gN1eIU%3D&t=4d5b0474&ps=13740610&shp=81f88b70&shcp=9b759fb9&idc=useast5&ftpl=1"]}, "imageWidth": 1200, "imageHeight": 1600}, {"imageURL": {"urlList": ["https://p16-common-sign.tiktokcdn-us.com/tos-alisg-i-photomode-sg/a600f0b591074ffeb948687ec5e9da00~tplv-photomode-image.jpeg?dr=9616&x-expires=1771110000&x-signature=UYiX246VxtByqE24fySjBZTvA3o%3D&t=4d5b0474&ps=13740610&shp=81f88b70&shcp=9b759fb9&idc=useast5&ftpl=1", "https://p19-common-sign.tiktokcdn-us.com/tos-alisg-i-photomode-sg/a600f0b591074ffeb948687ec5e9da00~tplv-photomode-image.jpeg?dr=9616&x-expires=1771110000&x-signature=jULesVPNtKFgkv063yl5dxkHoIs%3D&t=4d5b0474&ps=13740610&shp=81f88b70&shcp=9b759fb9&idc=useast5&ftpl=1"]}, "imageWidth": 1200, "imageHeight": 1600}], "cover": {"imageURL": {"urlList": ["https://p16-common-sign.tiktokcdn-us.com/tos-alisg-i-photomode-sg/6fd5a54c94b740109e0344c05d44ec5b~tplv-photomode-image.jpeg?dr=9616&x-expires=1771110000&x-signature=dIgQYU5Duvxl8BmhHcyxfeKRUG0%3D&t=4d5b0474&ps=13740610&shp=81f88b70&shcp=9b759fb9&idc=useast5&ftpl=1", "https://p19-common-sign.tiktokcdn-us.com/tos-alisg-i-photomode-sg/6fd5a54c94b740109e0344c05d44ec5b~tplv-photomode-image.jpeg?dr=9616&x-expires=1771110000&x-signature=YhqsBQSJKqS9ToQKt0iR0NJXmQI%3D&t=4d5b0474&ps=13740610&shp=81f88b70&shcp=9b759fb9&idc=useast5&ftpl=1"]}, "imageWidth": 2304, "imageHeight": 3072}, "shareCover": {"imageURL": {"urlList": ["https://p16-common-sign.tiktokcdn-us.com/tos-alisg-i-photomode-sg/6fd5a54c94b740109e0344c05d44ec5b~tplv-photomode-image.jpeg?dr=9616&x-expires=1771110000&x-signature=dIgQYU5Duvxl8BmhHcyxfeKRUG0%3D&t=4d5b0474&ps=13740610&shp=81f88b70&shcp=9b759fb9&idc=useast5&ftpl=1", "https://p19-common-sign.tiktokcdn-us.com/tos-alisg-i-photomode-sg/6fd5a54c94b740109e0344c05d44ec5b~tplv-photomode-image.jpeg?dr=9616&x-expires=1771110000&x-signature=YhqsBQSJKqS9ToQKt0iR0NJXmQI%3D&t=4d5b0474&ps=13740610&shp=81f88b70&shcp=9b759fb9&idc=useast5&ftpl=1"]}, "imageWidth": 2304, "imageHeight": 3072}, "title": ""}, "locationCreated": "LA", "suggestedWords": [], "contents": [{"desc": "\u0e2b\u0e25\u0e27\u0e07\u0e1e\u0e23\u0e30\u0e1a\u0e32\u0e07\u200b\u0e2a\u0e2d\u0e07\u0e27\u0e31\u0e19\u0e2b\u0e19\u0e36\u0e48\u0e07\u200b\u0e04\u0e37\u0e19\u200b  ep2", "textExtra": []}, {"desc": "#\u0e2b\u0e25\u0e27\u0e07\u0e1e\u0e23\u0e30\u0e1a\u0e32\u0e07\u0e40\u0e21\u0e37\u0e2d\u0e07\u0e21\u0e23\u0e14\u0e01\u0e42\u0e25\u0e01 #\u0e2d\u0e32\u0e2b\u0e32\u0e23\u0e1a\u0e49\u0e32\u0e19\u0e46 #jubulin ", "textExtra": [{"awemeId": "", "start": 0, "end": 23, "hashtagId": "1680077585051650", "hashtagName": "\u0e2b\u0e25\u0e27\u0e07\u0e1e\u0e23\u0e30\u0e1a\u0e32\u0e07\u0e40\u0e21\u0e37\u0e2d\u0e07\u0e21\u0e23\u0e14\u0e01\u0e42\u0e25\u0e01", "type": 1, "subType": 0, "isCommerce": false}, {"awemeId": "", "start": 24, "end": 35, "hashtagId": "1601796731667458", "hashtagName": "\u0e2d\u0e32\u0e2b\u0e32\u0e23\u0e1a\u0e49\u0e32\u0e19\u0e46", "type": 1, "subType": 0, "isCommerce": false}, {"awemeId": "", "start": 36, "end": 44, "hashtagId": "1704653037601801", "hashtagName": "jubulin", "type": 1, "subType": 0, "isCommerce": false}]}], "collected": false, "channelTags": [], "item_control": {"can_repost": true}, "IsAigc": false, "AIGCDescription": "", "backendSourceEventTracking": "", "CategoryType": 120, "textLanguage": "th", "textTranslatable": true, "titleLanguage": "", "titleTranslatable": false, "authorStatsV2": {"followerCount": "88", "followingCount": "229", "heart": "728", "heartCount": "728", "videoCount": "82", "diggCount": "603", "friendCount": "0"}, "isReviewing": false, "creatorAIComment": {"hasAITopic": false, "categoryList": [], "eligibleVideo": false, "notEligibleReason": 101}}}, "shareMeta": {"title": "Jubulin on TikTok", "desc": "\u0e2b\u0e25\u0e27\u0e07\u0e1e\u0e23\u0e30\u0e1a\u0e32\u0e07\u200b\u0e2a\u0e2d\u0e07\u0e27\u0e31\u0e19\u0e2b\u0e19\u0e36\u0e48\u0e07\u200b\u0e04\u0e37\u0e19\u200b  ep2 #\u0e2b\u0e25\u0e27\u0e07\u0e1e\u0e23\u0e30\u0e1a\u0e32\u0e07\u0e40\u0e21\u0e37\u0e2d\u0e07\u0e21\u0e23\u0e14\u0e01\u0e42\u0e25\u0e01 #\u0e2d\u0e32\u0e2b\u0e32\u0e23\u0e1a\u0e49\u0e32\u0e19\u0e46 #jubulin "}, "statusCode": 0, "statusMsg": ""}