{"itemInfo": {"itemStruct": {"id": "7400463144830766344", "desc": "", "createTime": "1723054602", "scheduleTime": 0, "video": {"id": "7400463144830766344", "height": 1024, "width": 576, "duration": 14, "ratio": "540p", "cover": "https://p19-common-sign.tiktokcdn-us.com/tos-alisg-p-0037/ogzfEDrERI9AgUgfj2EA0IDmrTuFEB97Bgplus~tplv-tiktokx-origin.image?dr=9636&x-expires=1769860800&x-signature=dh%2Fsr%2BW1DTagx21pIyt50IIXjZM%3D&t=4d5b0474&ps=13740610&shp=81f88b70&shcp=43f4a2f9&idc=useast5", "originCover": "https://p19-common-sign.tiktokcdn-us.com/tos-alisg-p-0037/a7314ebac31447d9986716adb1c527a6_1723054604~tplv-tiktokx-origin.image?dr=9636&x-expires=1769860800&x-signature=z0Y5hzeA0nRKdudYQGRUMsKHDzE%3D&t=4d5b0474&ps=13740610&shp=81f88b70&shcp=43f4a2f9&idc=useast5", "dynamicCover": "https://p19-common-sign.tiktokcdn-us.com/tos-alisg-p-0037/c6d160f9eb78473abf2edacd5c1bf83a_1723054604~tplv-tiktokx-origin.image?dr=9636&x-expires=1769860800&x-signature=5jj04n6ueJxUdK5Rglu1liVxFUA%3D&t=4d5b0474&ps=13740610&shp=81f88b70&shcp=43f4a2f9&idc=useast5", "playAddr": "https://v16-webapp-prime.us.tiktok.com/video/tos/alisg/tos-alisg-pve-0037c001/oE7Byf9fGzKmFBAjIlguRuEDgE5EU7L09IsIEt/?a=1988&bti=ODszNWYuMDE6&ch=0&cr=3&dr=0&lr=all&cd=0%7C0%7C0%7C&br=828&bt=414&cs=0&ds=6&ft=4KJMyMzm8Zmo07hz5x4jVd4jdpWrKsd.&mime_type=video_mp4&qs=4&rc=PDk2NDc7ZDNnM2dnZ2g2NUBpMzdraGs5cnl1dDMzODczNEA1NC42Yy1iXzYxYTNiXi80YSNrcmRzMmRjZm1gLS1kMTFzcw%3D%3D&btag=e000b8000&expire=1769864189&l=20260129125614E1780D5EBFA96C2FFC04&ply_type=2&policy=2&signature=5c65b7c3fd083e36aa566e92dbb12deb&tk=tt_chain_token", "downloadAddr": "https://v16-webapp-prime.us.tiktok.com/video/tos/alisg/tos-alisg-pve-0037c001/oYVDLBGeLCJ7ZdnuijNcACeI7HRQIogeAN3ouI/?a=1988&bti=ODszNWYuMDE6&ch=0&cr=3&dr=0&lr=all&cd=0%7C0%7C0%7C&br=1426&bt=713&cs=0&ds=3&ft=4KJMyMzm8Zmo07hz5x4jVd4jdpWrKsd.&mime_type=video_mp4&qs=0&rc=OmkzODY8ODY3Z2g1aDhpOEBpMzdraGs5cnl1dDMzODczNEA1YF81Nl4vNjYxNF9eXzZeYSNrcmRzMmRjZm1gLS1kMTFzcw%3D%3D&btag=e000b8000&expire=1769864189&l=20260129125614E1780D5EBFA96C2FFC04&ply_type=2&policy=2&signature=611ecf233a5a64f61c7cc709a29c74b9&tk=tt_chain_token", "shareCover": [""], "reflowCover": "", "bitrate": 424537, "encodedType": "normal", "format": "mp4", "videoQuality": "lower", "encodeUserTag": "", "codecType": "h264", "definition": "540p", "subtitleInfos": [], "zoomCover": {"240": "https://p19-common-sign.tiktokcdn-us.com/tos-alisg-p-0037/ogzfEDrERI9AgUgfj2EA0IDmrTuFEB97Bgplus~tplv-photomode-zoomcover:240:240.avif?dr=9616&x-expires=1769860800&x-signature=0UYiA%2FUfryWqWwoVxnSrd%2FQqhso%3D&t=4d5b0474&ps=13740610&shp=81f88b70&shcp=43f4a2f9&idc=useast5&ftpl=1", "480": "https://p19-common-sign.tiktokcdn-us.com/tos-alisg-p-0037/ogzfEDrERI9AgUgfj2EA0IDmrTuFEB97Bgplus~tplv-photomode-zoomcover:480:480.avif?dr=9616&x-expires=1769860800&x-signature=s5E%2BtsLyfNpYb6LHU5v1oaf%2FKGE%3D&t=4d5b0474&ps=13740610&shp=81f88b70&shcp=43f4a2f9&idc=useast5&ftpl=1", "720": "https://p19-common-sign.tiktokcdn-us.com/tos-alisg-p-0037/ogzfEDrERI9AgUgfj2EA0IDmrTuFEB97Bgplus~tplv-photomode-zoomcover:720:720.avif?dr=9616&x-expires=1769860800&x-signature=9oAOf9dfCVEGABwWNDdgYIwUNRE%3D&t=4d5b0474&ps=13740610&shp=81f88b70&shcp=43f4a2f9&idc=useast5&ftpl=1", "960": "https://p19-common-sign.tiktokcdn-us.com/tos-alisg-p-0037/ogzfEDrERI9AgUgfj2EA0IDmrTuFEB97Bgplus~tplv-photomode-zoomcover:960:960.avif?dr=9616&x-expires=1769860800&x-signature=NYroBLODMCS8X3gS6dYKWxy4fSU%3D&t=4d5b0474&ps=13740610&shp=81f88b70&shcp=43f4a2f9&idc=useast5&ftpl=1"}, "volumeInfo": {"Loudness": -13.1, "Peak": 0.71614}, "bitrateInfo": [{"Bitrate": 424537, "QualityType": 24, "BitrateFPS": 16, "GearName": "lower_540_0", "PlayAddr": {"DataSize": "772817", "Width": 576, "Height": 1024, "Uri": "v14044g50000cqprivfog65hveghu4n0", "UrlList": ["https://v16-webapp-prime.us.tiktok.com/video/tos/alisg/tos-alisg-pve-0037c001/oE7Byf9fGzKmFBAjIlguRuEDgE5EU7L09IsIEt/?a=1988&bti=ODszNWYuMDE6&ch=0&cr=3&dr=0&lr=all&cd=0%7C0%7C0%7C&br=828&bt=414&cs=0&ds=6&ft=4KJMyMzm8Zmo07hz5x4jVd4jdpWrKsd.&mime_type=video_mp4&qs=4&rc=PDk2NDc7ZDNnM2dnZ2g2NUBpMzdraGs5cnl1dDMzODczNEA1NC42Yy1iXzYxYTNiXi80YSNrcmRzMmRjZm1gLS1kMTFzcw%3D%3D&btag=e000b8000&expire=1769864189&l=20260129125614E1780D5EBFA96C2FFC04&ply_type=2&policy=2&signature=5c65b7c3fd083e36aa566e92dbb12deb&tk=tt_chain_token", "https://v19-webapp-prime.us.tiktok.com/video/tos/alisg/tos-alisg-pve-0037c001/oE7Byf9fGzKmFBAjIlguRuEDgE5EU7L09IsIEt/?a=1988&bti=ODszNWYuMDE6&ch=0&cr=3&dr=0&lr=all&cd=0%7C0%7C0%7C&br=828&bt=414&cs=0&ds=6&ft=4KJMyMzm8Zmo07hz5x4jVd4jdpWrKsd.&mime_type=video_mp4&qs=4&rc=PDk2NDc7ZDNnM2dnZ2g2NUBpMzdraGs5cnl1dDMzODczNEA1NC42Yy1iXzYxYTNiXi80YSNrcmRzMmRjZm1gLS1kMTFzcw%3D%3D&btag=e000b8000&expire=1769864189&l=20260129125614E1780D5EBFA96C2FFC04&ply_type=2&policy=2&signature=5c65b7c3fd083e36aa566e92dbb12deb&tk=tt_chain_token", "https://www.tiktok.com/aweme/v1/play/?faid=1988&file_id=7223aeed6ddd409db0ea08f491137689&is_play_url=1&item_id=7400463144830766344&line=0&ply_type=2&signaturev3=dmlkZW9faWQ7ZmlsZV9pZDtpdGVtX2lkLjRjZGNlMjVkMzhiNTkzODdhYzUwOTYxZjg2YmExMjI2&tk=tt_chain_token&video_id=v14044g50000cqprivfog65hveghu4n0"], "UrlKey": "v14044g50000cqprivfog65hveghu4n0_h264_540p_424537", "FileHash": "f6a1a59e08052bdf2aa973c7192251c6", "FileCs": "c:0-9362-c940"}, "CodecType": "h264", "MVMAF": "", "Format": "mp4", "VideoExtra": "{\"PktOffsetMap\":\"[{\\\"time\\\": 1, \\\"offset\\\": 28201}, {\\\"time\\\": 2, \\\"offset\\\": 89223}, {\\\"time\\\": 3, \\\"offset\\\": 273945}, {\\\"time\\\": 4, \\\"offset\\\": 465445}, {\\\"time\\\": 5, \\\"offset\\\": 556569}, {\\\"time\\\": 10, \\\"offset\\\": 749927}]\",\"mvmaf\":\"\",\"ufq\":\"\",\"volume_info_json\":\"\",\"transcode_feature_id\":\"5ec63939750549e79a31eb386fafda76\",\"dec_info\":\"\",\"gearvqm\":\"\",\"audio_bit_rate\":32475}"}, {"Bitrate": 316169, "QualityType": 25, "BitrateFPS": 16, "GearName": "lowest_540_0", "PlayAddr": {"DataSize": "575547", "Width": 576, "Height": 1024, "Uri": "v14044g50000cqprivfog65hveghu4n0", "UrlList": ["https://v16-webapp-prime.us.tiktok.com/video/tos/alisg/tos-alisg-pve-0037c001/ooyf7FlCAgfR1DjEEuuB99DIutEEsmtUgIBzI0/?a=1988&bti=ODszNWYuMDE6&ch=0&cr=3&dr=0&lr=all&cd=0%7C0%7C0%7C&br=616&bt=308&cs=0&ds=6&ft=4KJMyMzm8Zmo07hz5x4jVd4jdpWrKsd.&mime_type=video_mp4&qs=5&rc=PDhpOzs8N2c4Ozg1M2c1NkBpMzdraGs5cnl1dDMzODczNEBiMWFhNWIuNjAxYl8yMi5jYSNrcmRzMmRjZm1gLS1kMTFzcw%3D%3D&btag=e000b8000&expire=1769864189&l=20260129125614E1780D5EBFA96C2FFC04&ply_type=2&policy=2&signature=80529c3f5f1664622077e6f8270e9f18&tk=tt_chain_token", "https://v19-webapp-prime.us.tiktok.com/video/tos/alisg/tos-alisg-pve-0037c001/ooyf7FlCAgfR1DjEEuuB99DIutEEsmtUgIBzI0/?a=1988&bti=ODszNWYuMDE6&ch=0&cr=3&dr=0&lr=all&cd=0%7C0%7C0%7C&br=616&bt=308&cs=0&ds=6&ft=4KJMyMzm8Zmo07hz5x4jVd4jdpWrKsd.&mime_type=video_mp4&qs=5&rc=PDhpOzs8N2c4Ozg1M2c1NkBpMzdraGs5cnl1dDMzODczNEBiMWFhNWIuNjAxYl8yMi5jYSNrcmRzMmRjZm1gLS1kMTFzcw%3D%3D&btag=e000b8000&expire=1769864189&l=20260129125614E1780D5EBFA96C2FFC04&ply_type=2&policy=2&signature=80529c3f5f1664622077e6f8270e9f18&tk=tt_chain_token", "https://www.tiktok.com/aweme/v1/play/?faid=1988&file_id=f3125d50b2e548359d14e988d8df45e9&is_play_url=1&item_id=7400463144830766344&line=0&ply_type=2&signaturev3=dmlkZW9faWQ7ZmlsZV9pZDtpdGVtX2lkLmIxOTBlZWM1NGQyMWEyN2Y1YmYwYmZhZWY4N2ZjZGYx&tk=tt_chain_token&video_id=v14044g50000cqprivfog65hveghu4n0"], "UrlKey": "v14044g50000cqprivfog65hveghu4n0_h264_540p_316169", "FileHash": "a4a737193043d920d237b5ac660af682", "FileCs": "c:0-9362-d26c"}, "CodecType": "h264", "MVMAF": "", "Format": "mp4", "VideoExtra": "{\"PktOffsetMap\":\"[{\\\"time\\\": 1, \\\"offset\\\": 26355}, {\\\"time\\\": 2, \\\"offset\\\": 74662}, {\\\"time\\\": 3, \\\"offset\\\": 225452}, {\\\"time\\\": 4, \\\"offset\\\": 374837}, {\\\"time\\\": 5, \\\"offset\\\": 433595}, {\\\"time\\\": 10, \\\"offset\\\": 554549}]\",\"mvmaf\":\"\",\"ufq\":\"\",\"volume_info_json\":\"\",\"transcode_feature_id\":\"5ec63939750549e79a31eb386fafda76\",\"dec_info\":\"\",\"gearvqm\":\"\",\"audio_bit_rate\":32475}"}], "size": "772817", "VQScore": "57.02", "claInfo": {"hasOriginalAudio": false, "enableAutoCaption": true, "captionInfos": [], "noCaptionReason": 3}, "videoID": "v14044g50000cqprivfog65hveghu4n0", "PlayAddrStruct": {"DataSize": "772817", "Width": 576, "Height": 1024, "Uri": "v14044g50000cqprivfog65hveghu4n0", "UrlList": ["https://v16-webapp-prime.us.tiktok.com/video/tos/alisg/tos-alisg-pve-0037c001/oE7Byf9fGzKmFBAjIlguRuEDgE5EU7L09IsIEt/?a=1988&bti=ODszNWYuMDE6&ch=0&cr=3&dr=0&lr=all&cd=0%7C0%7C0%7C&br=828&bt=414&cs=0&ds=6&ft=4KJMyMzm8Zmo07hz5x4jVd4jdpWrKsd.&mime_type=video_mp4&qs=4&rc=PDk2NDc7ZDNnM2dnZ2g2NUBpMzdraGs5cnl1dDMzODczNEA1NC42Yy1iXzYxYTNiXi80YSNrcmRzMmRjZm1gLS1kMTFzcw%3D%3D&btag=e000b8000&expire=1769864189&l=20260129125614E1780D5EBFA96C2FFC04&ply_type=2&policy=2&signature=5c65b7c3fd083e36aa566e92dbb12deb&tk=tt_chain_token", "https://v19-webapp-prime.us.tiktok.com/video/tos/alisg/tos-alisg-pve-0037c001/oE7Byf9fGzKmFBAjIlguRuEDgE5EU7L09IsIEt/?a=1988&bti=ODszNWYuMDE6&ch=0&cr=3&dr=0&lr=all&cd=0%7C0%7C0%7C&br=828&bt=414&cs=0&ds=6&ft=4KJMyMzm8Zmo07hz5x4jVd4jdpWrKsd.&mime_type=video_mp4&qs=4&rc=PDk2NDc7ZDNnM2dnZ2g2NUBpMzdraGs5cnl1dDMzODczNEA1NC42Yy1iXzYxYTNiXi80YSNrcmRzMmRjZm1gLS1kMTFzcw%3D%3D&btag=e000b8000&expire=1769864189&l=20260129125614E1780D5EBFA96C2FFC04&ply_type=2&policy=2&signature=5c65b7c3fd083e36aa566e92dbb12deb&tk=tt_chain_token", "https://www.tiktok.com/aweme/v1/play/?faid=1988&file_id=7223aeed6ddd409db0ea08f491137689&is_play_url=1&item_id=7400463144830766344&line=0&ply_type=2&signaturev3=dmlkZW9faWQ7ZmlsZV9pZDtpdGVtX2lkLjRjZGNlMjVkMzhiNTkzODdhYzUwOTYxZjg2YmExMjI2&tk=tt_chain_token&video_id=v14044g50000cqprivfog65hveghu4n0"], "UrlKey": "v14044g50000cqprivfog65hveghu4n0_h264_540p_424537", "FileHash": "f6a1a59e08052bdf2aa973c7192251c6", "FileCs": "c:0-9362-c940"}}, "author": {"id": "7180734898821989381", "shortId": "", "uniqueId": ".md.rahim.ahmed", "nickname": "\ud83d\udc96\ud83d\udd25 \u09ac\u09be\u09b2\u09be\u0997\u099e\u09cd\u099c\u09bf \u09ab\u09c1\u09df\u09be\ud83d\udd25\ud83d\udc96", "avatarLarger": "https://p19-common-sign.tiktokcdn-us.com/tos-alisg-avt-0068/8b2f680a076ea4302b69e7aeb7489b60~tplv-tiktokx-cropcenter:1080:1080.jpeg?dr=9640&refresh_token=34301e9d&x-expires=1769860800&x-signature=qHF7IzbqMb3g8dQlUGolPypyj10%3D&t=4d5b0474&ps=13740610&shp=a5d48078&shcp=81f88b70&idc=useast5", "avatarMedium": "https://p19-common-sign.tiktokcdn-us.com/tos-alisg-avt-0068/8b2f680a076ea4302b69e7aeb7489b60~tplv-tiktokx-cropcenter:720:720.jpeg?dr=9640&refresh_token=e8158342&x-expires=1769860800&x-signature=OBivyW77yJjSM8W9WAisBZTw0jE%3D&t=4d5b0474&ps=13740610&shp=a5d48078&shcp=81f88b70&idc=useast5", "avatarThumb": "https://p19-common-sign.tiktokcdn-us.com/tos-alisg-avt-0068/8b2f680a076ea4302b69e7aeb7489b60~tplv-tiktokx-cropcenter:100:100.jpeg?dr=9640&refresh_token=63b1d2ea&x-expires=1769860800&x-signature=0loCx06Z2Wk0sOeGdlxkN3h936k%3D&t=4d5b0474&ps=13740610&shp=a5d48078&shcp=81f88b70&idc=useast5", "signature": "\u2764\ufe0f\ud83e\udef6\ud83e\udd19\u2764\ufe0f\ud83d\udd25 SYLHETI FUYA\u2764\ufe0f\ud83e\udef6\ud83e\udd19\u2764\ufe0f\ud83d\udd25", "createTime": 1672071400, "verified": false, "secUid": "MS4wLjABAAAAuTEtwL3DLzrdYfDVqaKt6knO0rI0paWEQ5Nyv-Oua_wpANtC74JVm1u7zSoMkpqt", "ftc": false, "relation": 0, "openFavorite": false, "commentSetting": 0, "duetSetting": 0, "stitchSetting": 0, "privateAccount": false, "secret": false, "isADVirtual": false, "roomId": "", "uniqueIdModifyTime": 0, "ttSeller": false, "downloadSetting": 0, "recommendReason": "", "nowInvitationCardUrl": "", "nickNameModifyTime": 0, "isEmbedBanned": false, "canExpPlaylist": false, "suggestAccountBind": false, "UserStoryStatus": 0}, "music": {"id": "7313892878252608258", "title": "original sound", "playUrl": "https://v16m.tiktokcdn-us.com/0c2bb4b004653e1e35e0fca3a5c3f871/697bad5d/video/tos/useast5/tos-useast5-v-27dcd7c799-tx/ogCBrtDMFAuTgKA7AJj5CB9UyslEEQAfglCeSE/?a=1233&bti=ODszNWYuMDE6&ch=0&cr=0&dr=0&er=0&lr=default&cd=0%7C0%7C0%7C0&br=252&bt=126&ds=5&ft=GSDrKInz7The_EwPXq8Zmo&mime_type=audio_mpeg&qs=13&rc=amhxcXA5cm41cDMzODU8NEBpamhxcXA5cm41cDMzODU8NEBwb2hgMmRzaS1gLS1kMS1zYSNwb2hgMmRzaS1gLS1kMS1zcw%3D%3D&vvpl=1&l=20260129125614E1780D5EBFA96C2FFC04&btag=e00070000", "coverLarge": "https://p19-common-sign.tiktokcdn-us.com/tos-alisg-avt-0068/3cec8a4c31efcc7f710bedc16f37a63f~tplv-tiktokx-cropcenter:1080:1080.jpeg?dr=9640&refresh_token=49490ef7&x-expires=1769860800&x-signature=byU%2FjTzGP3IpT72norQuEB%2BaNfI%3D&t=4d5b0474&ps=13740610&shp=a5d48078&shcp=81f88b70&idc=useast5", "coverMedium": "https://p19-common-sign.tiktokcdn-us.com/tos-alisg-avt-0068/3cec8a4c31efcc7f710bedc16f37a63f~tplv-tiktokx-cropcenter:720:720.jpeg?dr=9640&refresh_token=3d95a390&x-expires=1769860800&x-signature=qk2pMVEmdosDbEj4I1Ci43b0XME%3D&t=4d5b0474&ps=13740610&shp=a5d48078&shcp=81f88b70&idc=useast5", "coverThumb": "https://p19-common-sign.tiktokcdn-us.com/tos-alisg-avt-0068/3cec8a4c31efcc7f710bedc16f37a63f~tplv-tiktokx-cropcenter:100:100.jpeg?dr=9640&refresh_token=e00c1b30&x-expires=1769860800&x-signature=UWre7Y7AMdNGc3g%2FldJ4HpxSMmg%3D&t=4d5b0474&ps=13740610&shp=a5d48078&shcp=81f88b70&idc=useast5", "authorName": "ISQ", "original": true, "private": false, "duration": 14, "scheduleSearchTime": 0, "collected": false, "preciseDuration": {"preciseDuration": 14.497938, "preciseShootDuration": 14.497938, "preciseAuditionDuration": 14.497938, "preciseVideoDuration": 14.497938}, "isCopyrighted": false, "tt2dsp": {"tt_to_dsp_song_infos": []}}, "challenges": [], "stats": {"diggCount": 13, "shareCount": 0, "commentCount": 2, "playCount": 56, "collectCount": "0"}, "statsV2": {"diggCount": "13", "shareCount": "0", "commentCount": "2", "playCount": "56", "collectCount": "0", "repostCount": "0"}, "warnInfo": [], "originalItem": false, "officalItem": false, "textExtra": [], "secret": false, "forFriend": false, "digged": false, "itemCommentStatus": 0, "takeDown": 0, "effectStickers": [{"name": "Photo Double Animation", "ID": "303863263"}, {"name": "dont cry", "ID": "1562462"}], "authorStats": {"followerCount": 2646, "followingCount": 635, "heart": 90200, "heartCount": 90200, "videoCount": 1845, "diggCount": 103200, "friendCount": 0}, "privateItem": false, "duetEnabled": true, "stitchEnabled": true, "stickersOnItem": [], "isAd": false, "shareEnabled": true, "comments": [], "duetDisplay": 0, "stitchDisplay": 0, "diversificationLabels": ["Random Shoot", "Others"], "locationCreated": "BD", "suggestedWords": [], "contents": [], "diversificationId": 10075, "anchors": [{"id": "1562462", "type": 28, "keyword": "dont cry", "icon": {"uri": "tiktok-obj/capcut_logo_64px_bk.png", "urlList": ["https://p19-common-sign.tiktokcdn-us.com/tiktok-obj/capcut_logo_64px_bk.png~tplv-tiktokx-origin.image?dr=9627&x-expires=1769709600&x-signature=kGAIWYkylEv6FpyeMmnQqICxwzE%3D&t=4d5b0474&ps=13740610&shp=81f88b70&shcp=9b759fb9&idc=useast5", "https://p16-common-sign.tiktokcdn-us.com/tiktok-obj/capcut_logo_64px_bk.png~tplv-tiktokx-origin.image?dr=9627&x-expires=1769709600&x-signature=Qv%2Fif7bgNViMKixc25IcTdhaSLo%3D&t=4d5b0474&ps=13740610&shp=81f88b70&shcp=9b759fb9&idc=useast5", "https://p19-common-sign.tiktokcdn-us.com/tiktok-obj/capcut_logo_64px_bk.png~tplv-tiktokx-origin.jpeg?dr=9627&x-expires=1769709600&x-signature=fiWCD9sccgc429zL4UEcY2Dsg1c%3D&t=4d5b0474&ps=13740610&shp=81f88b70&shcp=9b759fb9&idc=useast5"]}, "schema": "https://www.capcut.com", "description": "Effects", "thumbnail": {"uri": "tiktok-obj/64px_anchor_effect3x.png", "urlList": ["https://p19-common-sign.tiktokcdn-us.com/tiktok-obj/64px_anchor_effect3x.png~tplv-tiktokx-origin.image?dr=9627&x-expires=1769709600&x-signature=VgBIBBVvox80eaN%2FN6qmTq97EYE%3D&t=4d5b0474&ps=13740610&shp=81f88b70&shcp=9b759fb9&idc=useast5", "https://p16-common-sign.tiktokcdn-us.com/tiktok-obj/64px_anchor_effect3x.png~tplv-tiktokx-origin.image?dr=9627&x-expires=1769709600&x-signature=FiUUTnrUCvaz%2B6%2F060dcHjjjJBA%3D&t=4d5b0474&ps=13740610&shp=81f88b70&shcp=9b759fb9&idc=useast5", "https://p19-common-sign.tiktokcdn-us.com/tiktok-obj/64px_anchor_effect3x.png~tplv-tiktokx-origin.jpeg?dr=9627&x-expires=1769709600&x-signature=LLY52UHSAAk7duDquvkfTFaZa1U%3D&t=4d5b0474&ps=13740610&shp=81f88b70&shcp=9b759fb9&idc=useast5"], "width": 64, "height": 64}, "extraInfo": {"subtype": ""}}], "collected": false, "channelTags": [], "item_control": {"can_repost": true}, "IsAigc": false, "AIGCDescription": "", "backendSourceEventTracking": "", "CategoryType": 120, "textLanguage": "un", "textTranslatable": false, "authorStatsV2": {"followerCount": "2646", "followingCount": "635", "heart": "90200", "heartCount": "90200", "videoCount": "1845", "diggCount": "103200", "friendCount": "0"}, "isReviewing": false, "creatorAIComment": {"hasAITopic": false, "categoryList": [], "eligibleVideo": false, "notEligibleReason": 101}}}, "shareMeta": {"title": "\ud83d\udc96\ud83d\udd25 \u09ac\u09be\u09b2\u09be\u0997\u099e\u09cd\u099c\u09bf \u09ab\u09c1\u09df\u09be\ud83d\udd25\ud83d\udc96 on TikTok", "desc": "\ud83d\udc96\ud83d\udd25 \u09ac\u09be\u09b2\u09be\u0997\u099e\u09cd\u099c\u09bf \u09ab\u09c1\u09df\u09be\ud83d\udd25\ud83d\udc96's short video with \u266c original sound"}, "statusCode": 0, "statusMsg": ""}