{"itemInfo": {"itemStruct": {"id": "7452310722337426706", "desc": "", "createTime": "1735126308", "scheduleTime": 0, "video": {"id": "7452310722337426706", "height": 1024, "width": 576, "duration": 7, "ratio": "540p", "cover": "https://p19-common-sign.tiktokcdn-us.com/tos-alisg-p-0037/oI842PtjAu4AirBTYEAAZBSEX81IYHOBi7Ntv~tplv-tiktokx-origin.image?dr=9636&x-expires=1769320800&x-signature=85ffocYwu2N%2F9eldsqavK3aHypU%3D&t=4d5b0474&ps=13740610&shp=81f88b70&shcp=43f4a2f9&idc=useast5", "originCover": "https://p19-common-sign.tiktokcdn-us.com/tos-alisg-p-0037/oE01Df5cIEK4QS7axBOAFC4rQFjeAfwARDaAx2~tplv-tiktokx-origin.image?dr=9636&x-expires=1769320800&x-signature=Kdi9IpfcuaEOud1fAgQz3GWKvao%3D&t=4d5b0474&ps=13740610&shp=81f88b70&shcp=43f4a2f9&idc=useast5", "dynamicCover": "https://p19-common-sign.tiktokcdn-us.com/tos-alisg-p-0037/osAj51EZxQxGdr4SI40c72AQDfAnFDBawCeOeQ~tplv-tiktokx-origin.image?dr=9636&x-expires=1769320800&x-signature=7gckdpU2zx69P4yew5dipmqN2wU%3D&t=4d5b0474&ps=13740610&shp=81f88b70&shcp=43f4a2f9&idc=useast5", "playAddr": "https://v16-webapp-prime.us.tiktok.com/video/tos/alisg/tos-alisg-pve-0037c001/oIBYWdwX7IkAi4EEtVN82ZYi8EvGBASPHrA4g/?a=1988&bti=ODszNWYuMDE6&ch=0&cr=3&dr=0&lr=all&cd=0%7C0%7C0%7C&cv=1&br=618&bt=309&cs=0&ds=6&ft=aEeq8qT0mIoPD12FpoRs3wUSLRAbMeF~O5&mime_type=video_mp4&qs=4&rc=aTw5OTs0ODM5ZDxnOTllZkBpM2c2aXY5cjp4dzMzODczNEBgMC80YS4zXy0xYjQzLzYtYSMtZDBwMmQ0bmlgLS1kMWBzcw%3D%3D&btag=e000b0000&expire=1769323585&l=2026012306461842067E803C5CC908A33E&ply_type=2&policy=2&signature=6bbdae50fbaa70504bb4d115824fd957&tk=tt_chain_token", "downloadAddr": "", "shareCover": [""], "reflowCover": "", "bitrate": 317394, "encodedType": "normal", "format": "mp4", "videoQuality": "lower", "encodeUserTag": "", "codecType": "h264", "definition": "540p", "subtitleInfos": [], "zoomCover": {"240": "https://p19-common-sign.tiktokcdn-us.com/tos-alisg-p-0037/oI842PtjAu4AirBTYEAAZBSEX81IYHOBi7Ntv~tplv-photomode-zoomcover:240:240.avif?dr=9616&x-expires=1769320800&x-signature=GTfkqyruDrAqXoh5AaIUlsB9uSk%3D&t=4d5b0474&ps=13740610&shp=81f88b70&shcp=43f4a2f9&idc=useast5&ftpl=1", "480": "https://p19-common-sign.tiktokcdn-us.com/tos-alisg-p-0037/oI842PtjAu4AirBTYEAAZBSEX81IYHOBi7Ntv~tplv-photomode-zoomcover:480:480.avif?dr=9616&x-expires=1769320800&x-signature=RMG7ZrFUpmbtI%2BgsSKZNSXMzKlg%3D&t=4d5b0474&ps=13740610&shp=81f88b70&shcp=43f4a2f9&idc=useast5&ftpl=1", "720": "https://p19-common-sign.tiktokcdn-us.com/tos-alisg-p-0037/oI842PtjAu4AirBTYEAAZBSEX81IYHOBi7Ntv~tplv-photomode-zoomcover:720:720.avif?dr=9616&x-expires=1769320800&x-signature=RxwL7Ync8GxGMowNZ9GgZ2%2BMuvM%3D&t=4d5b0474&ps=13740610&shp=81f88b70&shcp=43f4a2f9&idc=useast5&ftpl=1", "960": "https://p19-common-sign.tiktokcdn-us.com/tos-alisg-p-0037/oI842PtjAu4AirBTYEAAZBSEX81IYHOBi7Ntv~tplv-photomode-zoomcover:960:960.avif?dr=9616&x-expires=1769320800&x-signature=7ELTmS2mvGucKIEA7PJ8t3GUZSA%3D&t=4d5b0474&ps=13740610&shp=81f88b70&shcp=43f4a2f9&idc=useast5&ftpl=1"}, "volumeInfo": {"Loudness": -18, "Peak": 0.62373}, "bitrateInfo": [{"Bitrate": 317394, "QualityType": 24, "BitrateFPS": 19, "GearName": "lower_540_0", "PlayAddr": {"DataSize": "283751", "Width": 576, "Height": 1024, "Uri": "v1c044g50000ctluq77og65ssf33gd00", "UrlList": ["https://v16-webapp-prime.us.tiktok.com/video/tos/alisg/tos-alisg-pve-0037c001/oIBYWdwX7IkAi4EEtVN82ZYi8EvGBASPHrA4g/?a=1988&bti=ODszNWYuMDE6&ch=0&cr=3&dr=0&lr=all&cd=0%7C0%7C0%7C&cv=1&br=618&bt=309&cs=0&ds=6&ft=aEeq8qT0mIoPD12FpoRs3wUSLRAbMeF~O5&mime_type=video_mp4&qs=4&rc=aTw5OTs0ODM5ZDxnOTllZkBpM2c2aXY5cjp4dzMzODczNEBgMC80YS4zXy0xYjQzLzYtYSMtZDBwMmQ0bmlgLS1kMWBzcw%3D%3D&btag=e000b0000&expire=1769323585&l=2026012306461842067E803C5CC908A33E&ply_type=2&policy=2&signature=6bbdae50fbaa70504bb4d115824fd957&tk=tt_chain_token", "https://v19-webapp-prime.us.tiktok.com/video/tos/alisg/tos-alisg-pve-0037c001/oIBYWdwX7IkAi4EEtVN82ZYi8EvGBASPHrA4g/?a=1988&bti=ODszNWYuMDE6&ch=0&cr=3&dr=0&lr=all&cd=0%7C0%7C0%7C&cv=1&br=618&bt=309&cs=0&ds=6&ft=aEeq8qT0mIoPD12FpoRs3wUSLRAbMeF~O5&mime_type=video_mp4&qs=4&rc=aTw5OTs0ODM5ZDxnOTllZkBpM2c2aXY5cjp4dzMzODczNEBgMC80YS4zXy0xYjQzLzYtYSMtZDBwMmQ0bmlgLS1kMWBzcw%3D%3D&btag=e000b0000&expire=1769323585&l=2026012306461842067E803C5CC908A33E&ply_type=2&policy=2&signature=6bbdae50fbaa70504bb4d115824fd957&tk=tt_chain_token", "https://www.tiktok.com/aweme/v1/play/?faid=1988&file_id=0c9b26667de94a06b06511d8762639cf&is_play_url=1&item_id=7452310722337426706&line=0&ply_type=2&signaturev3=dmlkZW9faWQ7ZmlsZV9pZDtpdGVtX2lkLjkyMmQwZTAzNGQ3ZmZlOTAyNmUzMDkwMTkyYTRlN2M0&tk=tt_chain_token&video_id=v1c044g50000ctluq77og65ssf33gd00"], "UrlKey": "v1c044g50000ctluq77og65ssf33gd00_h264_540p_317394", "FileHash": "e165691c7ec23a1c70c9551e5dc8ea52", "FileCs": "c:0-6538-d669"}, "CodecType": "h264", "MVMAF": "{\"v2.0\": {\"srv1\": {\"v1080\": 80.265, \"v960\": 83.259, \"v864\": 86.235, \"v720\": 87.807}, \"ori\": {\"v1080\": 72.622, \"v960\": 77.51, \"v864\": 80.49, \"v720\": 83.96}}}", "Format": "mp4", "VideoExtra": "{\"PktOffsetMap\":\"[{\\\"time\\\": 1, \\\"offset\\\": 57948}, {\\\"time\\\": 2, \\\"offset\\\": 96590}, {\\\"time\\\": 3, \\\"offset\\\": 140741}, {\\\"time\\\": 4, \\\"offset\\\": 173141}, {\\\"time\\\": 5, \\\"offset\\\": 214014}]\",\"mvmaf\":\"{\\\"v2.0\\\": {\\\"srv1\\\": {\\\"v1080\\\": 80.265, \\\"v960\\\": 83.259, \\\"v864\\\": 86.235, \\\"v720\\\": 87.807}, \\\"ori\\\": {\\\"v1080\\\": 72.622, \\\"v960\\\": 77.51, \\\"v864\\\": 80.49, \\\"v720\\\": 83.96}}}\",\"ufq\":\"\",\"volume_info_json\":\"\",\"transcode_feature_id\":\"13b7b37dea7241b0b7632fa88ed11584\",\"dec_info\":\"\",\"gearvqm\":\"\",\"audio_bit_rate\":33073}"}], "size": "283751", "VQScore": "49.45", "claInfo": {"hasOriginalAudio": false, "enableAutoCaption": true, "captionInfos": [], "noCaptionReason": 3}, "videoID": "v1c044g50000ctluq77og65ssf33gd00", "PlayAddrStruct": {"DataSize": "283751", "Width": 576, "Height": 1024, "Uri": "v1c044g50000ctluq77og65ssf33gd00", "UrlList": ["https://v16-webapp-prime.us.tiktok.com/video/tos/alisg/tos-alisg-pve-0037c001/oIBYWdwX7IkAi4EEtVN82ZYi8EvGBASPHrA4g/?a=1988&bti=ODszNWYuMDE6&ch=0&cr=3&dr=0&lr=all&cd=0%7C0%7C0%7C&cv=1&br=618&bt=309&cs=0&ds=6&ft=aEeq8qT0mIoPD12FpoRs3wUSLRAbMeF~O5&mime_type=video_mp4&qs=4&rc=aTw5OTs0ODM5ZDxnOTllZkBpM2c2aXY5cjp4dzMzODczNEBgMC80YS4zXy0xYjQzLzYtYSMtZDBwMmQ0bmlgLS1kMWBzcw%3D%3D&btag=e000b0000&expire=1769323585&l=2026012306461842067E803C5CC908A33E&ply_type=2&policy=2&signature=6bbdae50fbaa70504bb4d115824fd957&tk=tt_chain_token", "https://v19-webapp-prime.us.tiktok.com/video/tos/alisg/tos-alisg-pve-0037c001/oIBYWdwX7IkAi4EEtVN82ZYi8EvGBASPHrA4g/?a=1988&bti=ODszNWYuMDE6&ch=0&cr=3&dr=0&lr=all&cd=0%7C0%7C0%7C&cv=1&br=618&bt=309&cs=0&ds=6&ft=aEeq8qT0mIoPD12FpoRs3wUSLRAbMeF~O5&mime_type=video_mp4&qs=4&rc=aTw5OTs0ODM5ZDxnOTllZkBpM2c2aXY5cjp4dzMzODczNEBgMC80YS4zXy0xYjQzLzYtYSMtZDBwMmQ0bmlgLS1kMWBzcw%3D%3D&btag=e000b0000&expire=1769323585&l=2026012306461842067E803C5CC908A33E&ply_type=2&policy=2&signature=6bbdae50fbaa70504bb4d115824fd957&tk=tt_chain_token", "https://www.tiktok.com/aweme/v1/play/?faid=1988&file_id=0c9b26667de94a06b06511d8762639cf&is_play_url=1&item_id=7452310722337426706&line=0&ply_type=2&signaturev3=dmlkZW9faWQ7ZmlsZV9pZDtpdGVtX2lkLjkyMmQwZTAzNGQ3ZmZlOTAyNmUzMDkwMTkyYTRlN2M0&tk=tt_chain_token&video_id=v1c044g50000ctluq77og65ssf33gd00"], "UrlKey": "v1c044g50000ctluq77og65ssf33gd00_h264_540p_317394", "FileHash": "e165691c7ec23a1c70c9551e5dc8ea52", "FileCs": "c:0-6538-d669"}}, "author": {"id": "7140940973727515675", "shortId": "", "uniqueId": "malikmukhtar442", "nickname": "\u0645\u0644\u06a9 \u0645\u062e\u062a\u0627\u0631 \u067e\u06be\u0627 \u0644\u06cc\u06c1 \u0627\u0644\u0627 \u2764\ufe0f\ud83c\udf39\u2764\ufe0f\u2764\ufe0f", "avatarLarger": "https://p19-common-sign.tiktokcdn-us.com/tos-alisg-avt-0068/d4037068d4213ecd3c411d6f69d9e5a7~tplv-tiktokx-cropcenter:1080:1080.jpeg?dr=9640&refresh_token=f1d60edb&x-expires=1769320800&x-signature=9BXf8CJwjG%2B0%2FvgsQ%2Br3t7jsbI0%3D&t=4d5b0474&ps=13740610&shp=a5d48078&shcp=81f88b70&idc=useast5", "avatarMedium": "https://p19-common-sign.tiktokcdn-us.com/tos-alisg-avt-0068/d4037068d4213ecd3c411d6f69d9e5a7~tplv-tiktokx-cropcenter:720:720.jpeg?dr=9640&refresh_token=2e551aed&x-expires=1769320800&x-signature=3%2ByXVYAO3cENdOgO%2BKAOulUEnTM%3D&t=4d5b0474&ps=13740610&shp=a5d48078&shcp=81f88b70&idc=useast5", "avatarThumb": "https://p19-common-sign.tiktokcdn-us.com/tos-alisg-avt-0068/d4037068d4213ecd3c411d6f69d9e5a7~tplv-tiktokx-cropcenter:100:100.jpeg?dr=9640&refresh_token=7225bcf1&x-expires=1769320800&x-signature=nx4nwTfjF08IbgbGxzabrC7YlmI%3D&t=4d5b0474&ps=13740610&shp=a5d48078&shcp=81f88b70&idc=useast5", "signature": "Malik Mukhtar", "createTime": 1664720804, "verified": false, "secUid": "MS4wLjABAAAAeG88W2kro9v_mSdNCEBlIk0tNQ3jUL_k678-i5LzNr_qNZOr1WBihsuJzyVDRo-l", "ftc": false, "relation": 0, "openFavorite": true, "commentSetting": 0, "duetSetting": 0, "stitchSetting": 0, "privateAccount": false, "secret": false, "isADVirtual": false, "roomId": "", "uniqueIdModifyTime": 0, "ttSeller": false, "downloadSetting": 3, "recommendReason": "", "nowInvitationCardUrl": "", "nickNameModifyTime": 0, "isEmbedBanned": false, "canExpPlaylist": false, "suggestAccountBind": false, "UserStoryStatus": 1}, "music": {"id": "7396922169495685904", "title": "original sound", "playUrl": "https://v16m.tiktokcdn-us.com/f83a18bff76993e54e3e67a54b98d148/69736daf/video/tos/useast5/tos-useast5-ve-27dcd7c799-tx/o8rYnC5TyQFd5EMmmpFfBBgU2JQ9WsIHJPDeUE/?a=1233&bti=ODszNWYuMDE6&ch=0&cr=0&dr=0&er=0&lr=default&cd=0%7C0%7C0%7C0&br=250&bt=125&ft=GSDrKInz7ThYxImPXq8Zmo&mime_type=audio_mpeg&qs=6&rc=Ozg1ZjQ2OTllZ2Y2ZDozaEBpM3A6dHg5cjRsdDMzODU8NEAzLjZiNWAxXjExYTJfYC4uYSNqZ3MwMmQ0X2dgLS1kMS1zcw%3D%3D&vvpl=1&l=2026012306461842067E803C5CC908A33E&btag=e000b8000", "coverLarge": "https://p19-common-sign.tiktokcdn-us.com/tos-alisg-avt-0068/415174982b11e5856e56d2275d42101f~tplv-tiktokx-cropcenter:1080:1080.jpeg?dr=9640&refresh_token=d4aa0d3b&x-expires=1769320800&x-signature=o8m08zxsmc8hRD82MGi1kChcR5U%3D&t=4d5b0474&ps=13740610&shp=a5d48078&shcp=81f88b70&idc=useast5", "coverMedium": "https://p19-common-sign.tiktokcdn-us.com/tos-alisg-avt-0068/415174982b11e5856e56d2275d42101f~tplv-tiktokx-cropcenter:720:720.jpeg?dr=9640&refresh_token=f47d792c&x-expires=1769320800&x-signature=LHMdZN1xdc%2BapE3hXn42Q81AhFI%3D&t=4d5b0474&ps=13740610&shp=a5d48078&shcp=81f88b70&idc=useast5", "coverThumb": "https://p19-common-sign.tiktokcdn-us.com/tos-alisg-avt-0068/415174982b11e5856e56d2275d42101f~tplv-tiktokx-cropcenter:100:100.jpeg?dr=9640&refresh_token=9b6515b3&x-expires=1769320800&x-signature=UeXinbTXYkuVPnoXTTio4jfmf60%3D&t=4d5b0474&ps=13740610&shp=a5d48078&shcp=81f88b70&idc=useast5", "authorName": "Syed Shahid Taqi", "original": true, "private": false, "duration": 21, "scheduleSearchTime": 0, "collected": false, "preciseDuration": {"preciseDuration": 21.499, "preciseShootDuration": 21.499, "preciseAuditionDuration": 21.499, "preciseVideoDuration": 21.499}, "isCopyrighted": false, "tt2dsp": {"tt_to_dsp_song_infos": [{"ShowStrategy": "1", "Platform": 1, "SongId": "1867031536", "Token": {"AppleMusicToken": {"DeveloperToken": "eyJhbGciOiJFUzI1NiIsImtpZCI6Ikc2Q0dLMjdWQzMifQ.eyJleHAiOjE3NjkzMzIwMjQsImlhdCI6MTc2OTA3MjgyNCwiaXNzIjoiTUo3OTdEOFU2RiJ9.vblK1KlETVx0sUsgF0wuW0imlhUIHUNJ7WsngYenHCzROdr9k1Ubb2AGMBr08yISzEPDIhir65q3QCcpSd_UkA"}}, "MetaSongId": "7592301392721004561"}]}}, "challenges": [], "stats": {"diggCount": 20, "shareCount": 0, "commentCount": 1, "playCount": 114, "collectCount": "0"}, "statsV2": {"diggCount": "20", "shareCount": "0", "commentCount": "1", "playCount": "114", "collectCount": "0", "repostCount": "0"}, "warnInfo": [], "originalItem": false, "officalItem": false, "textExtra": [], "secret": false, "forFriend": false, "digged": false, "itemCommentStatus": 0, "takeDown": 0, "effectStickers": [{"name": "LEN 19", "ID": "311915468"}], "authorStats": {"followerCount": 2977, "followingCount": 2885, "heart": 204200, "heartCount": 204200, "videoCount": 8210, "diggCount": 50800, "friendCount": 0}, "privateItem": false, "duetEnabled": true, "stitchEnabled": true, "stickersOnItem": [], "isAd": false, "shareEnabled": true, "comments": [], "duetDisplay": 0, "stitchDisplay": 0, "indexEnabled": true, "locationCreated": "PK", "suggestedWords": [], "contents": [], "collected": false, "channelTags": [], "item_control": {"can_repost": true}, "IsAigc": false, "AIGCDescription": "", "backendSourceEventTracking": "", "CategoryType": 120, "textLanguage": "un", "textTranslatable": false, "authorStatsV2": {"followerCount": "2977", "followingCount": "2885", "heart": "204200", "heartCount": "204200", "videoCount": "8210", "diggCount": "50800", "friendCount": "0"}, "isReviewing": false, "creatorAIComment": {"hasAITopic": false, "categoryList": [], "eligibleVideo": false, "notEligibleReason": 101}}}, "shareMeta": {"title": "\u0645\u0644\u06a9 \u0645\u062e\u062a\u0627\u0631 \u067e\u06be\u0627 \u0644\u06cc\u06c1 \u0627\u0644\u0627 \u2764\ufe0f\ud83c\udf39\u2764\ufe0f\u2764\ufe0f on TikTok", "desc": "\u0645\u0644\u06a9 \u0645\u062e\u062a\u0627\u0631 \u067e\u06be\u0627 \u0644\u06cc\u06c1 \u0627\u0644\u0627 \u2764\ufe0f\ud83c\udf39\u2764\ufe0f\u2764\ufe0f's short video with \u266c original sound"}, "statusCode": 0, "statusMsg": ""}