{"itemInfo": {"itemStruct": {"id": "7459641824383110421", "desc": "", "createTime": "1736833224", "scheduleTime": 0, "video": {"id": "7459641824383110421", "height": 1024, "width": 576, "duration": 15, "ratio": "540p", "cover": "https://p19-common-sign.tiktokcdn-us.com/tos-alisg-p-0037/oQsitBoDPC895amFEd8frAIBIDNLfCfAOjQYEk~tplv-tiktokx-origin.image?dr=9636&x-expires=1770062400&x-signature=bReiuQflRcoBnUgZ5bH2kE1oub4%3D&t=4d5b0474&ps=13740610&shp=81f88b70&shcp=43f4a2f9&idc=useast5", "originCover": "https://p19-common-sign.tiktokcdn-us.com/tos-alisg-p-0037/oMkDiMDrFC5kCeLcyjcsACmIB9NQQoDfAPfOiE~tplv-tiktokx-origin.image?dr=9636&x-expires=1770062400&x-signature=Ic5OZat6sFhHToGW4fmC90UnTaQ%3D&t=4d5b0474&ps=13740610&shp=81f88b70&shcp=43f4a2f9&idc=useast5", "dynamicCover": "https://p19-common-sign.tiktokcdn-us.com/tos-alisg-p-0037/o85BQDiQsWFfDZkfIA9LOoPMe0jmCAAjEQNCFq~tplv-tiktokx-origin.image?dr=9636&x-expires=1770062400&x-signature=hNT5PKcJcMILqbxQ0lWSybIYxCU%3D&t=4d5b0474&ps=13740610&shp=81f88b70&shcp=43f4a2f9&idc=useast5", "playAddr": "https://v16-webapp-prime.us.tiktok.com/video/tos/alisg/tos-alisg-pve-0037c001/oUQNefzBDIkMsL9iAmFgoFjk5CfGPCDQEnAOIC/?a=1988&bti=ODszNWYuMDE6&ch=0&cr=3&dr=0&lr=all&cd=0%7C0%7C0%7C&cv=1&br=1226&bt=613&cs=0&ds=6&ft=4KJMyMzm8Zmo08Rgmx4jV5Q4dpWrKsd.&mime_type=video_mp4&qs=4&rc=NjtkZDhnPGY1NDo7NTo6NkBpM3Z1PHg5cjx5eDMzODczNEAwYi8uLTNhNjExXzY0LTBhYSNvM2xkMmQ0ZS9gLS1kMTFzcw%3D%3D&btag=e000b8000&expire=1770063037&l=2026013120102216D8897C631941052097&ply_type=2&policy=2&signature=db09bccf42f6c1bacab531b2667bb966&tk=tt_chain_token", "downloadAddr": "https://video-tcs-sg.tiktok.com/0a173abfcf1be4e716cade04462712fe/698104bd/kmoat/mps/logo/v2/r/p/v14044g50000cu2vh97og65ug9or6sr0/3e65a93fb2bd4450b11de6ea9aecff69/06f00c90f56885e76c87e73457576d16/mp4/main.mp4?a=1988&bti=ODszNWYuMDE6&ch=0&cr=3&dr=0&lr=all&cd=0%7C0%7C0%7C&cv=1&br=0&bt=0&cs=0&ds=3&eid=1286&ft=4KLsdMzm8Zmo08Rgmx4jV5Q4dpWrKsd.&mime_type=video_mp4&qs=0&rc=cnF8b2hsc2d3SkBwaHIxaDFybndmPGlmZGQ5ZzQzN2c1aTw4aEBpM3Z1PHg5cjx5eDMzODczNEBjRl5Nc3FePmJKYSNvYF90aHFmOiMzY2I2YmIuXzIxX18wXjMwYSNvM2xkMmQ0ZS9gLS1kMTFzcw%3D%3D&btag=e000b8000&definition=720p&du=15&item_id=7459641824383110421&l=2026013120102216D8897C631941052097&logo_type=tiktok_m&ply_type=2&policy=eyJ2bSI6MiwiY2siOiJ0dF9jaGFpbl90b2tlbiJ9&user_text=azharcheema611", "shareCover": [""], "reflowCover": "", "bitrate": 628486, "encodedType": "normal", "format": "mp4", "videoQuality": "lower", "encodeUserTag": "", "codecType": "h264", "definition": "540p", "subtitleInfos": [], "zoomCover": {"240": "https://p19-common-sign.tiktokcdn-us.com/tos-alisg-p-0037/oQsitBoDPC895amFEd8frAIBIDNLfCfAOjQYEk~tplv-photomode-zoomcover:240:240.avif?dr=9616&x-expires=1770062400&x-signature=BFEw0balaWzTxWddBLByAeVv0JQ%3D&t=4d5b0474&ps=13740610&shp=81f88b70&shcp=43f4a2f9&idc=useast5&ftpl=1", "480": "https://p19-common-sign.tiktokcdn-us.com/tos-alisg-p-0037/oQsitBoDPC895amFEd8frAIBIDNLfCfAOjQYEk~tplv-photomode-zoomcover:480:480.avif?dr=9616&x-expires=1770062400&x-signature=tTl0i25b3alqsFrhvjeTgmQu5qY%3D&t=4d5b0474&ps=13740610&shp=81f88b70&shcp=43f4a2f9&idc=useast5&ftpl=1", "720": "https://p19-common-sign.tiktokcdn-us.com/tos-alisg-p-0037/oQsitBoDPC895amFEd8frAIBIDNLfCfAOjQYEk~tplv-photomode-zoomcover:720:720.avif?dr=9616&x-expires=1770062400&x-signature=G5Cqh3HMnqrLHzqUtpdIQeH4Zc4%3D&t=4d5b0474&ps=13740610&shp=81f88b70&shcp=43f4a2f9&idc=useast5&ftpl=1", "960": "https://p19-common-sign.tiktokcdn-us.com/tos-alisg-p-0037/oQsitBoDPC895amFEd8frAIBIDNLfCfAOjQYEk~tplv-photomode-zoomcover:960:960.avif?dr=9616&x-expires=1770062400&x-signature=Cfv3vjxjb90Wv4uoRNkCMngY4vo%3D&t=4d5b0474&ps=13740610&shp=81f88b70&shcp=43f4a2f9&idc=useast5&ftpl=1"}, "volumeInfo": {"Loudness": -13.1, "Peak": 0.67608}, "bitrateInfo": [{"Bitrate": 628486, "QualityType": 24, "BitrateFPS": 17, "GearName": "lower_540_0", "PlayAddr": {"DataSize": "1183912", "Width": 576, "Height": 1024, "Uri": "v14044g50000cu2vh97og65ug9or6sr0", "UrlList": ["https://v16-webapp-prime.us.tiktok.com/video/tos/alisg/tos-alisg-pve-0037c001/oUQNefzBDIkMsL9iAmFgoFjk5CfGPCDQEnAOIC/?a=1988&bti=ODszNWYuMDE6&ch=0&cr=3&dr=0&lr=all&cd=0%7C0%7C0%7C&cv=1&br=1226&bt=613&cs=0&ds=6&ft=4KJMyMzm8Zmo08Rgmx4jV5Q4dpWrKsd.&mime_type=video_mp4&qs=4&rc=NjtkZDhnPGY1NDo7NTo6NkBpM3Z1PHg5cjx5eDMzODczNEAwYi8uLTNhNjExXzY0LTBhYSNvM2xkMmQ0ZS9gLS1kMTFzcw%3D%3D&btag=e000b8000&expire=1770063037&l=2026013120102216D8897C631941052097&ply_type=2&policy=2&signature=db09bccf42f6c1bacab531b2667bb966&tk=tt_chain_token", "https://v19-webapp-prime.us.tiktok.com/video/tos/alisg/tos-alisg-pve-0037c001/oUQNefzBDIkMsL9iAmFgoFjk5CfGPCDQEnAOIC/?a=1988&bti=ODszNWYuMDE6&ch=0&cr=3&dr=0&lr=all&cd=0%7C0%7C0%7C&cv=1&br=1226&bt=613&cs=0&ds=6&ft=4KJMyMzm8Zmo08Rgmx4jV5Q4dpWrKsd.&mime_type=video_mp4&qs=4&rc=NjtkZDhnPGY1NDo7NTo6NkBpM3Z1PHg5cjx5eDMzODczNEAwYi8uLTNhNjExXzY0LTBhYSNvM2xkMmQ0ZS9gLS1kMTFzcw%3D%3D&btag=e000b8000&expire=1770063037&l=2026013120102216D8897C631941052097&ply_type=2&policy=2&signature=db09bccf42f6c1bacab531b2667bb966&tk=tt_chain_token", "https://www.tiktok.com/aweme/v1/play/?faid=1988&file_id=d337077298b741429cd96d051a2ae833&is_play_url=1&item_id=7459641824383110421&line=0&ply_type=2&signaturev3=dmlkZW9faWQ7ZmlsZV9pZDtpdGVtX2lkLmQzYzMxOGNkNTI2NGQ2OThlZGU0ZDNjNDAzYzEzZDVj&tk=tt_chain_token&video_id=v14044g50000cu2vh97og65ug9or6sr0"], "UrlKey": "v14044g50000cu2vh97og65ug9or6sr0_h264_540p_628486", "FileHash": "cd1bd718e9e549c831ca460107e9a016", "FileCs": "c:0-11305-e0ab"}, "CodecType": "h264", "MVMAF": "{\"v2.0\": {\"srv1\": {\"v1080\": 92.228, \"v960\": 91.993, \"v864\": 92.923, \"v720\": 96.568}, \"ori\": {\"v1080\": 83.092, \"v960\": 82.396, \"v864\": 85.86, \"v720\": 87.788}}}", "Format": "mp4", "VideoExtra": "{\"PktOffsetMap\":\"[{\\\"time\\\": 1, \\\"offset\\\": 146603}, {\\\"time\\\": 2, \\\"offset\\\": 247589}, {\\\"time\\\": 3, \\\"offset\\\": 312431}, {\\\"time\\\": 4, \\\"offset\\\": 376933}, {\\\"time\\\": 5, \\\"offset\\\": 473040}, {\\\"time\\\": 10, \\\"offset\\\": 805884}]\",\"mvmaf\":\"{\\\"v2.0\\\": {\\\"srv1\\\": {\\\"v1080\\\": 92.228, \\\"v960\\\": 91.993, \\\"v864\\\": 92.923, \\\"v720\\\": 96.568}, \\\"ori\\\": {\\\"v1080\\\": 83.092, \\\"v960\\\": 82.396, \\\"v864\\\": 85.86, \\\"v720\\\": 87.788}}}\",\"ufq\":\"\",\"volume_info_json\":\"\",\"transcode_feature_id\":\"13b7b37dea7241b0b7632fa88ed11584\",\"dec_info\":\"\",\"gearvqm\":\"\",\"audio_bit_rate\":32480}"}], "size": "1183912", "VQScore": "50.88", "claInfo": {"hasOriginalAudio": false, "enableAutoCaption": true, "captionInfos": [], "noCaptionReason": 3}, "videoID": "v14044g50000cu2vh97og65ug9or6sr0", "PlayAddrStruct": {"DataSize": "1183912", "Width": 576, "Height": 1024, "Uri": "v14044g50000cu2vh97og65ug9or6sr0", "UrlList": ["https://v16-webapp-prime.us.tiktok.com/video/tos/alisg/tos-alisg-pve-0037c001/oUQNefzBDIkMsL9iAmFgoFjk5CfGPCDQEnAOIC/?a=1988&bti=ODszNWYuMDE6&ch=0&cr=3&dr=0&lr=all&cd=0%7C0%7C0%7C&cv=1&br=1226&bt=613&cs=0&ds=6&ft=4KJMyMzm8Zmo08Rgmx4jV5Q4dpWrKsd.&mime_type=video_mp4&qs=4&rc=NjtkZDhnPGY1NDo7NTo6NkBpM3Z1PHg5cjx5eDMzODczNEAwYi8uLTNhNjExXzY0LTBhYSNvM2xkMmQ0ZS9gLS1kMTFzcw%3D%3D&btag=e000b8000&expire=1770063037&l=2026013120102216D8897C631941052097&ply_type=2&policy=2&signature=db09bccf42f6c1bacab531b2667bb966&tk=tt_chain_token", "https://v19-webapp-prime.us.tiktok.com/video/tos/alisg/tos-alisg-pve-0037c001/oUQNefzBDIkMsL9iAmFgoFjk5CfGPCDQEnAOIC/?a=1988&bti=ODszNWYuMDE6&ch=0&cr=3&dr=0&lr=all&cd=0%7C0%7C0%7C&cv=1&br=1226&bt=613&cs=0&ds=6&ft=4KJMyMzm8Zmo08Rgmx4jV5Q4dpWrKsd.&mime_type=video_mp4&qs=4&rc=NjtkZDhnPGY1NDo7NTo6NkBpM3Z1PHg5cjx5eDMzODczNEAwYi8uLTNhNjExXzY0LTBhYSNvM2xkMmQ0ZS9gLS1kMTFzcw%3D%3D&btag=e000b8000&expire=1770063037&l=2026013120102216D8897C631941052097&ply_type=2&policy=2&signature=db09bccf42f6c1bacab531b2667bb966&tk=tt_chain_token", "https://www.tiktok.com/aweme/v1/play/?faid=1988&file_id=d337077298b741429cd96d051a2ae833&is_play_url=1&item_id=7459641824383110421&line=0&ply_type=2&signaturev3=dmlkZW9faWQ7ZmlsZV9pZDtpdGVtX2lkLmQzYzMxOGNkNTI2NGQ2OThlZGU0ZDNjNDAzYzEzZDVj&tk=tt_chain_token&video_id=v14044g50000cu2vh97og65ug9or6sr0"], "UrlKey": "v14044g50000cu2vh97og65ug9or6sr0_h264_540p_628486", "FileHash": "cd1bd718e9e549c831ca460107e9a016", "FileCs": "c:0-11305-e0ab"}}, "author": {"id": "7149906801646093339", "shortId": "", "uniqueId": "azharcheema611", "nickname": "azharcheema611", "avatarLarger": "https://p19-common-sign.tiktokcdn-us.com/tos-useast2a-avt-0068-giso/7149913598314643483~tplv-tiktokx-cropcenter:1080:1080.jpeg?dr=9640&refresh_token=43f248dd&x-expires=1770062400&x-signature=hJzNu0FyU3043Lti75Yi%2FJ6Ueu8%3D&t=4d5b0474&ps=13740610&shp=a5d48078&shcp=81f88b70&idc=useast5", "avatarMedium": "https://p19-common-sign.tiktokcdn-us.com/tos-useast2a-avt-0068-giso/7149913598314643483~tplv-tiktokx-cropcenter:720:720.jpeg?dr=9640&refresh_token=67b8c2ae&x-expires=1770062400&x-signature=4qsY2re0IH4I%2Bp2mi9HwYDW%2Faqo%3D&t=4d5b0474&ps=13740610&shp=a5d48078&shcp=81f88b70&idc=useast5", "avatarThumb": "https://p19-common-sign.tiktokcdn-us.com/tos-useast2a-avt-0068-giso/7149913598314643483~tplv-tiktokx-cropcenter:100:100.jpeg?dr=9640&refresh_token=deab4dff&x-expires=1770062400&x-signature=mcctDjcGrwFrwo5%2BvonCE4fad%2Bg%3D&t=4d5b0474&ps=13740610&shp=a5d48078&shcp=81f88b70&idc=useast5", "signature": "", "createTime": 1664718985, "verified": false, "secUid": "MS4wLjABAAAAbqKmYvSd5L-tEcce9AVD5E_0eCvqUg5TbF0zCn2V-oluDSHkYbbpE6bcuUGafeV6", "ftc": false, "relation": 0, "openFavorite": false, "commentSetting": 0, "duetSetting": 0, "stitchSetting": 0, "privateAccount": false, "secret": false, "isADVirtual": false, "roomId": "", "uniqueIdModifyTime": 0, "ttSeller": false, "downloadSetting": 0, "recommendReason": "", "nowInvitationCardUrl": "", "nickNameModifyTime": 0, "isEmbedBanned": false, "canExpPlaylist": false, "suggestAccountBind": false, "UserStoryStatus": 0}, "music": {"id": "7356370974121560878", "title": "original sound", "playUrl": "https://v16m.tiktokcdn-us.com/89474352f6a79feaf4e36fe44eac3a43/697eb621/video/tos/useast5/tos-useast5-v-27dcd7-tx/okPiZAA4BCiAlcAXAvCEEZiKglUuFcUAHyhUG/?a=1233&bti=ODszNWYuMDE6&ch=0&cr=0&dr=0&er=0&lr=default&cd=0%7C0%7C0%7C0&br=250&bt=125&ds=5&ft=GSDrKInz7ThnDb7PXq8Zmo&mime_type=audio_mpeg&qs=13&rc=am48amw5cnZrcjMzZzU8NEBpam48amw5cnZrcjMzZzU8NEBrZmVmMmQ0NV9gLS1kMS9zYSNrZmVmMmQ0NV9gLS1kMS9zcw%3D%3D&vvpl=1&l=2026013120102216D8897C631941052097&btag=e00078000", "coverLarge": "https://p19-common-sign.tiktokcdn-us.com/tos-useast8-avt-0068-tx2/09c6e304a80fa22ccaee4e230e59b754~tplv-tiktokx-cropcenter:1080:1080.jpeg?dr=9640&refresh_token=22f43372&x-expires=1770062400&x-signature=pms9QtMs1nWcs2ANsBjMks4q054%3D&t=4d5b0474&ps=13740610&shp=a5d48078&shcp=81f88b70&idc=useast5", "coverMedium": "https://p19-common-sign.tiktokcdn-us.com/tos-useast8-avt-0068-tx2/09c6e304a80fa22ccaee4e230e59b754~tplv-tiktokx-cropcenter:720:720.jpeg?dr=9640&refresh_token=25586ad0&x-expires=1770062400&x-signature=E%2Bg4AOnwSgoWb36sJOKGDComW5I%3D&t=4d5b0474&ps=13740610&shp=a5d48078&shcp=81f88b70&idc=useast5", "coverThumb": "https://p19-common-sign.tiktokcdn-us.com/tos-useast8-avt-0068-tx2/09c6e304a80fa22ccaee4e230e59b754~tplv-tiktokx-cropcenter:100:100.jpeg?dr=9640&refresh_token=64af51d7&x-expires=1770062400&x-signature=UUtfoJwMLkEuA4ghKSOwhppnDYM%3D&t=4d5b0474&ps=13740610&shp=a5d48078&shcp=81f88b70&idc=useast5", "authorName": "\ud83e\udd8b \ud83e\udd8b Mehak Malik \ud83e\udd8b\ud83e\udd8b", "original": true, "private": false, "duration": 19, "scheduleSearchTime": 0, "collected": false, "preciseDuration": {"preciseDuration": 19.04325, "preciseShootDuration": 19.04325, "preciseAuditionDuration": 19.04325, "preciseVideoDuration": 19.04325}, "isCopyrighted": false, "tt2dsp": {"tt_to_dsp_song_infos": []}}, "challenges": [], "stats": {"diggCount": 56, "shareCount": 0, "commentCount": 6, "playCount": 188, "collectCount": "0"}, "statsV2": {"diggCount": "56", "shareCount": "0", "commentCount": "6", "playCount": "188", "collectCount": "0", "repostCount": "0"}, "warnInfo": [], "originalItem": false, "officalItem": false, "textExtra": [], "secret": false, "forFriend": false, "digged": false, "itemCommentStatus": 0, "takeDown": 0, "effectStickers": [{"name": "High Filter", "ID": "977825666"}], "authorStats": {"followerCount": 2217, "followingCount": 5270, "heart": 42900, "heartCount": 42900, "videoCount": 769, "diggCount": 90800, "friendCount": 0}, "privateItem": false, "duetEnabled": true, "stitchEnabled": true, "stickersOnItem": [], "isAd": false, "shareEnabled": true, "comments": [], "duetDisplay": 0, "stitchDisplay": 0, "indexEnabled": true, "locationCreated": "PK", "suggestedWords": [], "contents": [], "anchors": [{"id": "977825666", "type": 28, "keyword": "High Filter", "icon": {"uri": "tiktok-obj/capcut_logo_64px_bk.png", "urlList": ["https://p19-common-sign.tiktokcdn-us.com/tiktok-obj/capcut_logo_64px_bk.png~tplv-tiktokx-origin.image?dr=9627&x-expires=1769911200&x-signature=pj9Fe%2BqQcSDSlU1WMWrc2kJAfTo%3D&t=4d5b0474&ps=13740610&shp=81f88b70&shcp=9b759fb9&idc=useast5", "https://p16-common-sign.tiktokcdn-us.com/tiktok-obj/capcut_logo_64px_bk.png~tplv-tiktokx-origin.image?dr=9627&x-expires=1769911200&x-signature=fqdVQUnDbLn7GsoQK0bvLrNo6uw%3D&t=4d5b0474&ps=13740610&shp=81f88b70&shcp=9b759fb9&idc=useast5", "https://p19-common-sign.tiktokcdn-us.com/tiktok-obj/capcut_logo_64px_bk.png~tplv-tiktokx-origin.jpeg?dr=9627&x-expires=1769911200&x-signature=6DWaf5f2aHYnTCac09JevqBlcqk%3D&t=4d5b0474&ps=13740610&shp=81f88b70&shcp=9b759fb9&idc=useast5"]}, "schema": "https://www.capcut.com", "description": "Effects", "thumbnail": {"uri": "tiktok-obj/64px_anchor_effect3x.png", "urlList": ["https://p19-common-sign.tiktokcdn-us.com/tiktok-obj/64px_anchor_effect3x.png~tplv-tiktokx-origin.image?dr=9627&x-expires=1769911200&x-signature=nzVwnPdS5%2FoPoo27%2FengLPFouRY%3D&t=4d5b0474&ps=13740610&shp=81f88b70&shcp=9b759fb9&idc=useast5", "https://p16-common-sign.tiktokcdn-us.com/tiktok-obj/64px_anchor_effect3x.png~tplv-tiktokx-origin.image?dr=9627&x-expires=1769911200&x-signature=IDIn3NyOETJ5vKBKRDu6QtE2t0Q%3D&t=4d5b0474&ps=13740610&shp=81f88b70&shcp=9b759fb9&idc=useast5", "https://p19-common-sign.tiktokcdn-us.com/tiktok-obj/64px_anchor_effect3x.png~tplv-tiktokx-origin.jpeg?dr=9627&x-expires=1769911200&x-signature=OVsrq%2F7p0W74n9ms6IULjqMI9nA%3D&t=4d5b0474&ps=13740610&shp=81f88b70&shcp=9b759fb9&idc=useast5"], "width": 64, "height": 64}, "extraInfo": {"subtype": ""}}], "collected": false, "channelTags": [], "item_control": {"can_repost": true}, "IsAigc": false, "AIGCDescription": "", "backendSourceEventTracking": "", "CategoryType": 120, "textLanguage": "un", "textTranslatable": false, "authorStatsV2": {"followerCount": "2217", "followingCount": "5270", "heart": "42900", "heartCount": "42900", "videoCount": "769", "diggCount": "90800", "friendCount": "0"}, "isReviewing": false, "creatorAIComment": {"hasAITopic": false, "categoryList": [], "eligibleVideo": false, "notEligibleReason": 101}}}, "shareMeta": {"title": "azharcheema611 on TikTok", "desc": "azharcheema611's short video with \u266c original sound"}, "statusCode": 0, "statusMsg": ""}