{"itemInfo": {"itemStruct": {"id": "7543902494372416790", "desc": "", "createTime": "1756451681", "scheduleTime": 0, "video": {"id": "7543902494372416790", "height": 1024, "width": 576, "duration": 14, "ratio": "540p", "cover": "https://p19-common-sign.tiktokcdn-us.com/tos-no1a-p-0037-no/oknKCfzZDFeoFA9EGxEUV9I2sBkQG4Mg6BRhNA~tplv-tiktokx-origin.image?dr=9636&x-expires=1771434000&x-signature=q93NLY5ji0sPNbw9yJ%2B4lQHbdNI%3D&t=4d5b0474&ps=13740610&shp=81f88b70&shcp=43f4a2f9&idc=useast5", "originCover": "https://p16-common-sign.tiktokcdn-us.com/tos-no1a-p-0037-no/oIZ2xAM8VkDJ9EQoesFfFBgczU4sN4QGRtD6EG~tplv-tiktokx-origin.image?dr=9636&x-expires=1771434000&x-signature=rhE5%2FKl0oOX1m3ObHzAdCGGR63E%3D&t=4d5b0474&ps=13740610&shp=81f88b70&shcp=43f4a2f9&idc=useast5", "dynamicCover": "https://p19-common-sign.tiktokcdn-us.com/tos-no1a-p-0037-no/oAsVfDsWQAkGGzFE6FpEiMNOaQFRgoF9oiBZ4f~tplv-tiktokx-origin.image?dr=9636&x-expires=1771434000&x-signature=nYtNbdBoq%2BEPQCd1T2PLMXHXy80%3D&t=4d5b0474&ps=13740610&shp=81f88b70&shcp=43f4a2f9&idc=useast5", "playAddr": "https://v16-webapp-prime.us.tiktok.com/video/tos/no1a/tos-no1a-ve-0068-no/oUfG0Z2mVoZwIgEcUemFGE4DBoB8sERxN6kAQF/?a=1988&bti=ODszNWYuMDE6&ch=0&cr=3&dr=0&lr=all&cd=0%7C0%7C0%7C&cv=1&br=2056&bt=1028&cs=0&ds=6&ft=4KJMyMzm8Zmo0CQzcx4jVL6ZdpWrKsd.&mime_type=video_mp4&qs=0&rc=PDNmOjM0NDdpOTg2M2U0NUBpM3N0bXc5cmtvNTMzbzczNUBfNF4vX2NiXi8xXmBiM2AyYSNyYDQuMmRrM2xhLS1kMTFzcw%3D%3D&btag=e000b8000&expire=1771434796&l=2026021617130284769B4C2CBB3AD6ED91&ply_type=2&policy=2&signature=d46e42c78d5b041663a530c6dc792d8a&tk=tt_chain_token", "downloadAddr": "https://video-tcs-va.tiktok.com/4154cdfb5f30491b72fd77016564ca66/6995f32c/kmoat/mps/logo/v2/r/p/v24044gl0000d2ol6hnog65t1j7qcpu0/910f5e4b1c15490da2d78bd5f4162ecf/700e00ac2600a9b51d7d114cde525e0a/mp4/main.mp4?a=1988&bti=ODszNWYuMDE6&ch=0&cr=3&dr=0&lr=all&cd=0%7C0%7C0%7C&cv=1&br=0&bt=0&cs=0&ds=3&eid=1286&ft=4KLsRMzm8Zmo0CQzcx4jVL6ZdpWrKsd.&mime_type=video_mp4&qs=0&rc=cnF8b2hsc2d3SkBwaHIxaDFybndmaWg5NzhlOjVnPDhmZWhpNEBpM3N0bXc5cmtvNTMzbzczNUBjRl5Nc3FePmJKYSNvYF90aHFmOiNgLy5jYTVhXi0xLi4xMi02YSNyYDQuMmRrM2xhLS1kMTFzcw%3D%3D&btag=e000b8000&definition=720p&du=15&item_id=7543902494372416790&l=2026021617130284769B4C2CBB3AD6ED91&logo_type=tiktok_m&ply_type=2&policy=eyJ2bSI6MiwiY2siOiJ0dF9jaGFpbl90b2tlbiJ9&user_text=murielmarty6", "shareCover": [""], "reflowCover": "", "bitrate": 1053027, "encodedType": "normal", "format": "mp4", "videoQuality": "normal", "encodeUserTag": "", "codecType": "h264", "definition": "540p", "subtitleInfos": [], "zoomCover": {"240": "https://p16-common-sign.tiktokcdn-us.com/tos-no1a-p-0037-no/oknKCfzZDFeoFA9EGxEUV9I2sBkQG4Mg6BRhNA~tplv-photomode-zoomcover:240:240.avif?dr=9616&x-expires=1771434000&x-signature=dgpW%2BcZkFKyvNJh2xl9%2BAiC3y7o%3D&t=4d5b0474&ps=13740610&shp=81f88b70&shcp=43f4a2f9&idc=useast5&ftpl=1", "480": "https://p16-common-sign.tiktokcdn-us.com/tos-no1a-p-0037-no/oknKCfzZDFeoFA9EGxEUV9I2sBkQG4Mg6BRhNA~tplv-photomode-zoomcover:480:480.avif?dr=9616&x-expires=1771434000&x-signature=sFq6dKx9sPx7zsk7LfDMiwhybVU%3D&t=4d5b0474&ps=13740610&shp=81f88b70&shcp=43f4a2f9&idc=useast5&ftpl=1", "720": "https://p19-common-sign.tiktokcdn-us.com/tos-no1a-p-0037-no/oknKCfzZDFeoFA9EGxEUV9I2sBkQG4Mg6BRhNA~tplv-photomode-zoomcover:720:720.avif?dr=9616&x-expires=1771434000&x-signature=MQxhgUSFKy1%2BurbYBhy3v1QFvyw%3D&t=4d5b0474&ps=13740610&shp=81f88b70&shcp=43f4a2f9&idc=useast5&ftpl=1", "960": "https://p16-common-sign.tiktokcdn-us.com/tos-no1a-p-0037-no/oknKCfzZDFeoFA9EGxEUV9I2sBkQG4Mg6BRhNA~tplv-photomode-zoomcover:960:960.avif?dr=9616&x-expires=1771434000&x-signature=lEmHssg99UYdL480H2%2BhodSDNTU%3D&t=4d5b0474&ps=13740610&shp=81f88b70&shcp=43f4a2f9&idc=useast5&ftpl=1"}, "volumeInfo": {"Loudness": -17.7, "Peak": 0.6166}, "bitrateInfo": [{"Bitrate": 1053027, "QualityType": 20, "BitrateFPS": 30, "GearName": "normal_540_0", "PlayAddr": {"DataSize": "1910323", "Width": 576, "Height": 1024, "Uri": "v24044gl0000d2ol6hnog65t1j7qcpu0", "UrlList": ["https://v16-webapp-prime.us.tiktok.com/video/tos/no1a/tos-no1a-ve-0068-no/oUfG0Z2mVoZwIgEcUemFGE4DBoB8sERxN6kAQF/?a=1988&bti=ODszNWYuMDE6&ch=0&cr=3&dr=0&lr=all&cd=0%7C0%7C0%7C&cv=1&br=2056&bt=1028&cs=0&ds=6&ft=4KJMyMzm8Zmo0CQzcx4jVL6ZdpWrKsd.&mime_type=video_mp4&qs=0&rc=PDNmOjM0NDdpOTg2M2U0NUBpM3N0bXc5cmtvNTMzbzczNUBfNF4vX2NiXi8xXmBiM2AyYSNyYDQuMmRrM2xhLS1kMTFzcw%3D%3D&btag=e000b8000&expire=1771434796&l=2026021617130284769B4C2CBB3AD6ED91&ply_type=2&policy=2&signature=d46e42c78d5b041663a530c6dc792d8a&tk=tt_chain_token", "https://v19-webapp-prime.us.tiktok.com/video/tos/no1a/tos-no1a-ve-0068-no/oUfG0Z2mVoZwIgEcUemFGE4DBoB8sERxN6kAQF/?a=1988&bti=ODszNWYuMDE6&ch=0&cr=3&dr=0&lr=all&cd=0%7C0%7C0%7C&cv=1&br=2056&bt=1028&cs=0&ds=6&ft=4KJMyMzm8Zmo0CQzcx4jVL6ZdpWrKsd.&mime_type=video_mp4&qs=0&rc=PDNmOjM0NDdpOTg2M2U0NUBpM3N0bXc5cmtvNTMzbzczNUBfNF4vX2NiXi8xXmBiM2AyYSNyYDQuMmRrM2xhLS1kMTFzcw%3D%3D&btag=e000b8000&expire=1771434796&l=2026021617130284769B4C2CBB3AD6ED91&ply_type=2&policy=2&signature=d46e42c78d5b041663a530c6dc792d8a&tk=tt_chain_token", "https://www.tiktok.com/aweme/v1/play/?faid=1988&file_id=52c16be0c3a5462fa4e1f1b027ac70b9&is_play_url=1&item_id=7543902494372416790&line=0&ply_type=2&signaturev3=dmlkZW9faWQ7ZmlsZV9pZDtpdGVtX2lkLjA0N2Y2NTAyNWQxNWEwOGFkM2RlZGUxOWE3YTgwMzYw&tk=tt_chain_token&video_id=v24044gl0000d2ol6hnog65t1j7qcpu0"], "UrlKey": "v24044gl0000d2ol6hnog65t1j7qcpu0_h264_540p_1053027", "FileHash": "729716a4d458ce837b1ec389913be3c5", "FileCs": "c:0-13393-ebde"}, "CodecType": "h264", "MVMAF": "{\"v2.0\": {\"srv1\": {\"v1080\": 96.349, \"v960\": 97.171, \"v864\": 98.523, \"v720\": 98.756}, \"ori\": {\"v1080\": 86.637, \"v960\": 88.759, \"v864\": 90.321, \"v720\": 92.934}}}", "Format": "mp4", "VideoExtra": "{\"PktOffsetMap\":\"[{\\\"time\\\": 1, \\\"offset\\\": 166293}, {\\\"time\\\": 2, \\\"offset\\\": 181975}, {\\\"time\\\": 3, \\\"offset\\\": 453656}, {\\\"time\\\": 4, \\\"offset\\\": 463284}, {\\\"time\\\": 5, \\\"offset\\\": 737232}, {\\\"time\\\": 10, \\\"offset\\\": 1580847}]\",\"mvmaf\":\"{\\\"v2.0\\\": {\\\"srv1\\\": {\\\"v1080\\\": 96.349, \\\"v960\\\": 97.171, \\\"v864\\\": 98.523, \\\"v720\\\": 98.756}, \\\"ori\\\": {\\\"v1080\\\": 86.637, \\\"v960\\\": 88.759, \\\"v864\\\": 90.321, \\\"v720\\\": 92.934}}}\",\"ufq\":\"{\\\"enh\\\":78.967,\\\"playback\\\":{\\\"ori\\\":69.604,\\\"srv1\\\":77.796},\\\"src\\\":78.967,\\\"trans\\\":69.604,\\\"version\\\":\\\"v1.1\\\"}\",\"volume_info_json\":\"\",\"transcode_feature_id\":\"1834aab9e1b0caae9362706a00ff9f52\",\"dec_info\":\"\",\"gearvqm\":\"\",\"audio_bit_rate\":32531}"}, {"Bitrate": 368794, "QualityType": 28, "BitrateFPS": 30, "GearName": "adapt_540_1", "PlayAddr": {"DataSize": "669039", "Width": 576, "Height": 1024, "Uri": "v24044gl0000d2ol6hnog65t1j7qcpu0", "UrlList": ["https://v16-webapp-prime.us.tiktok.com/video/tos/no1a/tos-no1a-ve-0068-no/oUt9UVXGDIe74x6NAMFUksRGzBfroaFQEhgZEs/?a=1988&bti=ODszNWYuMDE6&ch=0&cr=3&dr=0&lr=all&cd=0%7C0%7C0%7C&cv=1&br=720&bt=360&cs=2&ds=6&ft=4KJMyMzm8Zmo0CQzcx4jVL6ZdpWrKsd.&mime_type=video_mp4&qs=11&rc=aDxoaWg4OjhpNWRlZDpoOkBpM3N0bXc5cmtvNTMzbzczNUBgNGI1MWJjNi0xMTZeMF42YSNyYDQuMmRrM2xhLS1kMTFzcw%3D%3D&btag=e000b8000&expire=1771434796&l=2026021617130284769B4C2CBB3AD6ED91&ply_type=2&policy=2&signature=3ac633ecffdf23c654da2b663b6e9ae8&tk=tt_chain_token", "https://v19-webapp-prime.us.tiktok.com/video/tos/no1a/tos-no1a-ve-0068-no/oUt9UVXGDIe74x6NAMFUksRGzBfroaFQEhgZEs/?a=1988&bti=ODszNWYuMDE6&ch=0&cr=3&dr=0&lr=all&cd=0%7C0%7C0%7C&cv=1&br=720&bt=360&cs=2&ds=6&ft=4KJMyMzm8Zmo0CQzcx4jVL6ZdpWrKsd.&mime_type=video_mp4&qs=11&rc=aDxoaWg4OjhpNWRlZDpoOkBpM3N0bXc5cmtvNTMzbzczNUBgNGI1MWJjNi0xMTZeMF42YSNyYDQuMmRrM2xhLS1kMTFzcw%3D%3D&btag=e000b8000&expire=1771434796&l=2026021617130284769B4C2CBB3AD6ED91&ply_type=2&policy=2&signature=3ac633ecffdf23c654da2b663b6e9ae8&tk=tt_chain_token", "https://www.tiktok.com/aweme/v1/play/?faid=1988&file_id=97ae37aa9b4a420f95f7e54e8fee79ce&is_play_url=1&item_id=7543902494372416790&line=0&ply_type=2&signaturev3=dmlkZW9faWQ7ZmlsZV9pZDtpdGVtX2lkLjU5MjAzNWVkMGVhMDgyZmQwMTA2YWJmMDU1YzJkYzgy&tk=tt_chain_token&video_id=v24044gl0000d2ol6hnog65t1j7qcpu0"], "UrlKey": "v24044gl0000d2ol6hnog65t1j7qcpu0_bytevc1_540p_368794", "FileHash": "3deb442c88d04ca06f6c40bff23264ce", "FileCs": "c:0-13715-648c"}, "CodecType": "h265_hvc1", "MVMAF": "{\"v2.0\": {\"srv1\": {\"v1080\": 92.542, \"v960\": 94.111, \"v864\": 95.814, \"v720\": 97.815}, \"ori\": {\"v1080\": 80.994, \"v960\": 84.347, \"v864\": 87.407, \"v720\": 90.18}}}", "Format": "mp4", "VideoExtra": "{\"PktOffsetMap\":\"[{\\\"time\\\": 1, \\\"offset\\\": 94856}, {\\\"time\\\": 2, \\\"offset\\\": 112024}, {\\\"time\\\": 3, \\\"offset\\\": 181823}, {\\\"time\\\": 4, \\\"offset\\\": 191972}, {\\\"time\\\": 5, \\\"offset\\\": 286287}, {\\\"time\\\": 10, \\\"offset\\\": 504008}]\",\"mvmaf\":\"{\\\"v2.0\\\": {\\\"srv1\\\": {\\\"v1080\\\": 92.542, \\\"v960\\\": 94.111, \\\"v864\\\": 95.814, \\\"v720\\\": 97.815}, \\\"ori\\\": {\\\"v1080\\\": 80.994, \\\"v960\\\": 84.347, \\\"v864\\\": 87.407, \\\"v720\\\": 90.18}}}\",\"ufq\":\"{\\\"enh\\\":78.967,\\\"playback\\\":{\\\"ori\\\":64.962,\\\"srv1\\\":75.459},\\\"src\\\":78.967,\\\"trans\\\":64.962,\\\"version\\\":\\\"v1.2\\\"}\",\"volume_info_json\":\"\",\"transcode_feature_id\":\"181c568d189a8338c396a97b23e5de25\",\"dec_info\":\"\",\"gearvqm\":\"{\\\"v3.0\\\": {\\\"ori\\\": 91.211, \\\"sr20\\\": 99.749}}\",\"audio_bit_rate\":32531}"}], "size": "1910323", "VQScore": "64.8", "claInfo": {"hasOriginalAudio": false, "enableAutoCaption": true, "captionInfos": [], "noCaptionReason": 3}, "videoID": "v24044gl0000d2ol6hnog65t1j7qcpu0", "PlayAddrStruct": {"DataSize": "1910323", "Width": 576, "Height": 1024, "Uri": "v24044gl0000d2ol6hnog65t1j7qcpu0", "UrlList": ["https://v16-webapp-prime.us.tiktok.com/video/tos/no1a/tos-no1a-ve-0068-no/oUfG0Z2mVoZwIgEcUemFGE4DBoB8sERxN6kAQF/?a=1988&bti=ODszNWYuMDE6&ch=0&cr=3&dr=0&lr=all&cd=0%7C0%7C0%7C&cv=1&br=2056&bt=1028&cs=0&ds=6&ft=4KJMyMzm8Zmo0CQzcx4jVL6ZdpWrKsd.&mime_type=video_mp4&qs=0&rc=PDNmOjM0NDdpOTg2M2U0NUBpM3N0bXc5cmtvNTMzbzczNUBfNF4vX2NiXi8xXmBiM2AyYSNyYDQuMmRrM2xhLS1kMTFzcw%3D%3D&btag=e000b8000&expire=1771434796&l=2026021617130284769B4C2CBB3AD6ED91&ply_type=2&policy=2&signature=d46e42c78d5b041663a530c6dc792d8a&tk=tt_chain_token", "https://v19-webapp-prime.us.tiktok.com/video/tos/no1a/tos-no1a-ve-0068-no/oUfG0Z2mVoZwIgEcUemFGE4DBoB8sERxN6kAQF/?a=1988&bti=ODszNWYuMDE6&ch=0&cr=3&dr=0&lr=all&cd=0%7C0%7C0%7C&cv=1&br=2056&bt=1028&cs=0&ds=6&ft=4KJMyMzm8Zmo0CQzcx4jVL6ZdpWrKsd.&mime_type=video_mp4&qs=0&rc=PDNmOjM0NDdpOTg2M2U0NUBpM3N0bXc5cmtvNTMzbzczNUBfNF4vX2NiXi8xXmBiM2AyYSNyYDQuMmRrM2xhLS1kMTFzcw%3D%3D&btag=e000b8000&expire=1771434796&l=2026021617130284769B4C2CBB3AD6ED91&ply_type=2&policy=2&signature=d46e42c78d5b041663a530c6dc792d8a&tk=tt_chain_token", "https://www.tiktok.com/aweme/v1/play/?faid=1988&file_id=52c16be0c3a5462fa4e1f1b027ac70b9&is_play_url=1&item_id=7543902494372416790&line=0&ply_type=2&signaturev3=dmlkZW9faWQ7ZmlsZV9pZDtpdGVtX2lkLjA0N2Y2NTAyNWQxNWEwOGFkM2RlZGUxOWE3YTgwMzYw&tk=tt_chain_token&video_id=v24044gl0000d2ol6hnog65t1j7qcpu0"], "UrlKey": "v24044gl0000d2ol6hnog65t1j7qcpu0_h264_540p_1053027", "FileHash": "729716a4d458ce837b1ec389913be3c5", "FileCs": "c:0-13393-ebde"}}, "author": {"id": "6789911127418487813", "shortId": "", "uniqueId": "murielmarty6", "nickname": "Mumu", "avatarLarger": "https://p19-common-sign.tiktokcdn-us.com/tos-maliva-avt-0068/f488b36cb420f0e6673a44d553f14183~tplv-tiktokx-cropcenter:1080:1080.jpeg?dr=9640&refresh_token=7783e97e&x-expires=1771434000&x-signature=BD%2BwtSQbV31Qp11C8YMVdbYFdso%3D&t=4d5b0474&ps=13740610&shp=a5d48078&shcp=81f88b70&idc=useast5", "avatarMedium": "https://p16-common-sign.tiktokcdn-us.com/tos-maliva-avt-0068/f488b36cb420f0e6673a44d553f14183~tplv-tiktokx-cropcenter:720:720.jpeg?dr=9640&refresh_token=04ee39e7&x-expires=1771434000&x-signature=XgV6%2Bw%2Fi7i4llL89sgXktz6IxGY%3D&t=4d5b0474&ps=13740610&shp=a5d48078&shcp=81f88b70&idc=useast5", "avatarThumb": "https://p19-common-sign.tiktokcdn-us.com/tos-maliva-avt-0068/f488b36cb420f0e6673a44d553f14183~tplv-tiktokx-cropcenter:100:100.jpeg?dr=9640&refresh_token=678744d8&x-expires=1771434000&x-signature=qnFQzjMxJ%2Fu3zL2gltpfnVhq0G8%3D&t=4d5b0474&ps=13740610&shp=a5d48078&shcp=81f88b70&idc=useast5", "signature": "Fan de diamant painting, je passe des heures et des heures \u00e0 en faire", "createTime": 1580910888, "verified": false, "secUid": "MS4wLjABAAAA_InS1P0F-3N_tM18UD8TZLZkA3lrNrtViitSZUrhWBm7IsQlGPKiYQgLDlkCUo_r", "ftc": false, "relation": 0, "openFavorite": false, "commentSetting": 0, "duetSetting": 0, "stitchSetting": 0, "privateAccount": false, "secret": false, "isADVirtual": false, "roomId": "", "uniqueIdModifyTime": 0, "ttSeller": false, "downloadSetting": 0, "recommendReason": "", "nowInvitationCardUrl": "", "nickNameModifyTime": 0, "isEmbedBanned": false, "canExpPlaylist": false, "suggestAccountBind": false, "UserStoryStatus": 0}, "music": {"id": "7161499924138363690", "title": "original sound", "playUrl": "https://v16m.tiktokcdn-us.com/2cbcb98fc84cdf9e3c5836a71086fd12/6993a495/video/tos/useast5/tos-useast5-v-27dcd7-tx/2add1225433649eca6e8de0b4e404954/?a=1233&bti=ODszNWYuMDE6&ch=0&cr=0&dr=0&er=0&lr=default&cd=0%7C0%7C0%7C0&br=250&bt=125&ds=5&ft=GSDrKInz7ThVZEfPXq8Zmo&mime_type=audio_mp4&qs=13&rc=amw3N2Y6ZmxmZzMzZzU8NEBpamw3N2Y6ZmxmZzMzZzU8NEBoNnFqcjQwMWVgLS1kMS9zYSNoNnFqcjQwMWVgLS1kMS9zcw%3D%3D&vvpl=1&l=2026021617130284769B4C2CBB3AD6ED91&btag=e00078000", "coverLarge": "https://p16-common-sign.tiktokcdn-us.com/tos-useast5-avt-0068-tx/7350852114093965355~tplv-tiktokx-cropcenter:1080:1080.jpeg?dr=9640&refresh_token=f6a22ef6&x-expires=1771434000&x-signature=6xWogIW%2BjTQNsyPxwm%2BCndIQp9A%3D&t=4d5b0474&ps=13740610&shp=a5d48078&shcp=81f88b70&idc=useast5", "coverMedium": "https://p16-common-sign.tiktokcdn-us.com/tos-useast5-avt-0068-tx/7350852114093965355~tplv-tiktokx-cropcenter:720:720.jpeg?dr=9640&refresh_token=dcb65175&x-expires=1771434000&x-signature=%2BsAVW%2Ff%2Ft1PpBrKkTr9sYOFGpmI%3D&t=4d5b0474&ps=13740610&shp=a5d48078&shcp=81f88b70&idc=useast5", "coverThumb": "https://p19-common-sign.tiktokcdn-us.com/tos-useast5-avt-0068-tx/7350852114093965355~tplv-tiktokx-cropcenter:100:100.jpeg?dr=9640&refresh_token=eedbddb1&x-expires=1771434000&x-signature=OfXpkGPBNWPl1fEv68nr66xYGyY%3D&t=4d5b0474&ps=13740610&shp=a5d48078&shcp=81f88b70&idc=useast5", "authorName": "iAngelRagdolls", "original": true, "private": false, "duration": 23, "scheduleSearchTime": 0, "collected": false, "preciseDuration": {"preciseDuration": 23.98, "preciseShootDuration": 23.98, "preciseAuditionDuration": 23.98, "preciseVideoDuration": 23.98}, "isCopyrighted": true, "tt2dsp": {"tt_to_dsp_song_infos": []}, "is_unlimited_music": false, "is_commerce_music": true, "shoot_duration": 23}, "challenges": [], "stats": {"diggCount": 6, "shareCount": 0, "commentCount": 1, "playCount": 309, "collectCount": "0"}, "statsV2": {"diggCount": "6", "shareCount": "0", "commentCount": "1", "playCount": "309", "collectCount": "0", "repostCount": "0"}, "warnInfo": [], "originalItem": false, "officalItem": false, "textExtra": [], "secret": false, "forFriend": false, "digged": false, "itemCommentStatus": 0, "takeDown": 0, "effectStickers": [], "authorStats": {"followerCount": 239, "followingCount": 1387, "heart": 333, "heartCount": 333, "videoCount": 46, "diggCount": 19400, "friendCount": 0}, "privateItem": false, "duetEnabled": true, "stitchEnabled": true, "stickersOnItem": [], "isAd": false, "shareEnabled": true, "comments": [], "duetDisplay": 0, "stitchDisplay": 0, "indexEnabled": true, "diversificationLabels": ["Pets", "Animals", "Nature"], "locationCreated": "FR", "suggestedWords": [], "contents": [], "diversificationId": 10019, "collected": false, "channelTags": [], "item_control": {"can_repost": true}, "IsAigc": false, "AIGCDescription": "", "backendSourceEventTracking": "", "CategoryType": 113, "textLanguage": "un", "textTranslatable": false, "authorStatsV2": {"followerCount": "239", "followingCount": "1387", "heart": "333", "heartCount": "333", "videoCount": "46", "diggCount": "19400", "friendCount": "0"}, "isReviewing": false, "creatorAIComment": {"hasAITopic": false, "categoryList": [], "eligibleVideo": false, "notEligibleReason": 101}}}, "shareMeta": {"title": "Mumu on TikTok", "desc": "Mumu's short video with \u266c original sound"}, "statusCode": 0, "statusMsg": ""}