{"itemInfo": {"itemStruct": {"id": "7585294089885682966", "desc": "", "createTime": "1766088909", "scheduleTime": 0, "video": {"id": "7585294089885682966", "height": 0, "width": 0, "duration": 0, "ratio": "", "cover": "https://p16-common-sign.tiktokcdn-us.com/tos-no1a-i-photomode-no/9a5db9e6350a46db830f619db1e97454~tplv-photomode-image.jpeg?dr=9616&x-expires=1771423200&x-signature=CGUDofojgnfF%2Fs3PO1ALYc8kcKE%3D&t=4d5b0474&ps=13740610&shp=81f88b70&shcp=9b759fb9&idc=useast5&ftpl=1", "originCover": "https://p16-common-sign.tiktokcdn-us.com/tos-no1a-i-photomode-no/9a5db9e6350a46db830f619db1e97454~tplv-photomode-image.jpeg?dr=9616&x-expires=1771423200&x-signature=CGUDofojgnfF%2Fs3PO1ALYc8kcKE%3D&t=4d5b0474&ps=13740610&shp=81f88b70&shcp=9b759fb9&idc=useast5&ftpl=1", "dynamicCover": "", "playAddr": "", "downloadAddr": "", "shareCover": [""], "reflowCover": "", "zoomCover": {"240": "", "480": "", "720": "", "960": ""}}, "author": {"id": "6762069441193018374", "shortId": "", "uniqueId": "_s.m.g_2", "nickname": "napoletana", "avatarLarger": "https://p16-common-sign.tiktokcdn-us.com/tos-maliva-avt-0068/e72e8fe438d4c09c2516dbf65a1ec5ec~tplv-tiktokx-cropcenter:1080:1080.jpeg?dr=9640&refresh_token=4b2d719d&x-expires=1771423200&x-signature=bJMIPefYD67Jhm8Ipzyi6MpuHvI%3D&t=4d5b0474&ps=13740610&shp=a5d48078&shcp=81f88b70&idc=useast5", "avatarMedium": "https://p16-common-sign.tiktokcdn-us.com/tos-maliva-avt-0068/e72e8fe438d4c09c2516dbf65a1ec5ec~tplv-tiktokx-cropcenter:720:720.jpeg?dr=9640&refresh_token=27baca90&x-expires=1771423200&x-signature=voWxmiAXPbMGIlqykCxXYBgS3FU%3D&t=4d5b0474&ps=13740610&shp=a5d48078&shcp=81f88b70&idc=useast5", "avatarThumb": "https://p16-common-sign.tiktokcdn-us.com/tos-maliva-avt-0068/e72e8fe438d4c09c2516dbf65a1ec5ec~tplv-tiktokx-cropcenter:100:100.jpeg?dr=9640&refresh_token=1276c6a3&x-expires=1771423200&x-signature=%2Bg2RH536Dq%2BVKFrh39DtO1wNzgc%3D&t=4d5b0474&ps=13740610&shp=a5d48078&shcp=81f88b70&idc=useast5", "signature": "Mamma a tempo pieno\ud83d\udc68\u200d\ud83d\udc69\u200d\ud83d\udc67\u200d\ud83d\udc67\ud83d\udc95\nsusy\ud83d\udc97\n\ud83d\udc8b", "createTime": 1574388401, "verified": false, "secUid": "MS4wLjABAAAAZRblHOZUbwXI3GcQ62OpYo-59shCTwGZn2-IUL4b4el1sub96v1IP4sPkn9ak_Kz", "ftc": false, "relation": 0, "openFavorite": false, "commentSetting": 3, "duetSetting": 0, "stitchSetting": 0, "privateAccount": false, "secret": false, "isADVirtual": false, "roomId": "", "uniqueIdModifyTime": 0, "ttSeller": false, "downloadSetting": 0, "recommendReason": "", "nowInvitationCardUrl": "", "nickNameModifyTime": 0, "isEmbedBanned": false, "canExpPlaylist": false, "suggestAccountBind": false, "UserStoryStatus": 1}, "music": {"id": "7515118681958812438", "title": "suono originale", "playUrl": "https://v16m.tiktokcdn-us.com/caa97ccdd45c3abea7b0cc6223321cb1/69937cb9/video/tos/no1a/tos-no1a-v-2370-no/oEClIIVIG3MFiDIIAIeVEQAARLfZAQLowVYTfW/?a=1233&bti=ODszNWYuMDE6&ch=0&cr=0&dr=0&er=0&lr=default&cd=0%7C0%7C0%7C0&br=250&bt=125&ds=5&ft=GSDrKInz7Th7fifPXq8Zmo&mime_type=audio_mpeg&qs=13&rc=MzdodW85cmRrNDMzbzU8NUBpMzdodW85cmRrNDMzbzU8NUAzZTRjMmRrLjJhLS1kMTFzYSMzZTRjMmRrLjJhLS1kMTFzcw%3D%3D&vvpl=1&l=2026021614222113E8FCD18DCD507A73D8&btag=e00050000", "coverLarge": "https://p16-common-sign.tiktokcdn-us.com/tos-maliva-avt-0068/9529d854854565e2bb756de7cb6f3d62~tplv-tiktokx-cropcenter:1080:1080.jpeg?dr=9640&refresh_token=d474dbd4&x-expires=1771423200&x-signature=aHRNf3nnaEDoAr6TC8PdsoZK4lg%3D&t=4d5b0474&ps=13740610&shp=a5d48078&shcp=81f88b70&idc=useast5", "coverMedium": "https://p16-common-sign.tiktokcdn-us.com/tos-maliva-avt-0068/9529d854854565e2bb756de7cb6f3d62~tplv-tiktokx-cropcenter:720:720.jpeg?dr=9640&refresh_token=d717c976&x-expires=1771423200&x-signature=0%2Bs9HPaCzbfJQ6AqrGtvqFmy5mM%3D&t=4d5b0474&ps=13740610&shp=a5d48078&shcp=81f88b70&idc=useast5", "coverThumb": "https://p19-common-sign.tiktokcdn-us.com/tos-maliva-avt-0068/9529d854854565e2bb756de7cb6f3d62~tplv-tiktokx-cropcenter:100:100.jpeg?dr=9640&refresh_token=feed70ae&x-expires=1771423200&x-signature=j9UgNMR8VVj7QVXE0BhbwegUPow%3D&t=4d5b0474&ps=13740610&shp=a5d48078&shcp=81f88b70&idc=useast5", "authorName": "\u00c8 la Vita...", "original": true, "private": false, "duration": 60, "scheduleSearchTime": 0, "collected": false, "preciseDuration": {"preciseDuration": 60.630188, "preciseShootDuration": 60.630188, "preciseAuditionDuration": 60.630188, "preciseVideoDuration": 60.630188}, "isCopyrighted": true, "tt2dsp": {"tt_to_dsp_song_infos": [{"ShowStrategy": "1", "Platform": 1, "SongId": "262213115", "Token": {"AppleMusicToken": {"DeveloperToken": "eyJhbGciOiJFUzI1NiIsImtpZCI6Ikc2Q0dLMjdWQzMifQ.eyJleHAiOjE3NzEzMzkxNTMsImlhdCI6MTc3MTA3OTk1MywiaXNzIjoiTUo3OTdEOFU2RiJ9.EWxYXwXyuylzkXmR53vaeBKPoIZT7TsPH7c6ZTESfbFGk5S4O0XJjdUYOVbW907zTWLf3uE93wwTKo05kTOYEA"}}, "MetaSongId": "6701926781286369281"}, {"ShowStrategy": "1", "Platform": 3, "SongId": "061G1Z2YsE7onCdj18Lqmq", "MetaSongId": "6701926781286369281"}]}, "is_unlimited_music": false, "is_commerce_music": true, "shoot_duration": 60}, "challenges": [], "stats": {"diggCount": 7, "shareCount": 0, "commentCount": 0, "playCount": 339, "collectCount": "0"}, "statsV2": {"diggCount": "7", "shareCount": "0", "commentCount": "0", "playCount": "339", "collectCount": "0", "repostCount": "0"}, "warnInfo": [], "originalItem": false, "officalItem": false, "textExtra": [], "secret": false, "forFriend": false, "digged": false, "itemCommentStatus": 3, "takeDown": 0, "effectStickers": [], "authorStats": {"followerCount": 8034, "followingCount": 6320, "heart": 218800, "heartCount": 218800, "videoCount": 15000, "diggCount": 230900, "friendCount": 0}, "privateItem": false, "stickersOnItem": [], "isAd": false, "shareEnabled": true, "comments": [], "duetDisplay": 0, "stitchDisplay": 0, "indexEnabled": true, "imagePost": {"images": [{"imageURL": {"urlList": ["https://p16-common-sign.tiktokcdn-us.com/tos-no1a-i-photomode-no/9a5db9e6350a46db830f619db1e97454~tplv-photomode-image.jpeg?dr=9616&x-expires=1771423200&x-signature=CGUDofojgnfF%2Fs3PO1ALYc8kcKE%3D&t=4d5b0474&ps=13740610&shp=81f88b70&shcp=9b759fb9&idc=useast5&ftpl=1", "https://p19-common-sign.tiktokcdn-us.com/tos-no1a-i-photomode-no/9a5db9e6350a46db830f619db1e97454~tplv-photomode-image.jpeg?dr=9616&x-expires=1771423200&x-signature=vbSjZg%2Bw2FQ7rMUbm8VwW3NQtGU%3D&t=4d5b0474&ps=13740610&shp=81f88b70&shcp=9b759fb9&idc=useast5&ftpl=1"]}, "imageWidth": 1080, "imageHeight": 2030}], "cover": {"imageURL": {"urlList": ["https://p16-common-sign.tiktokcdn-us.com/tos-no1a-i-photomode-no/9a5db9e6350a46db830f619db1e97454~tplv-photomode-image.jpeg?dr=9616&x-expires=1771423200&x-signature=CGUDofojgnfF%2Fs3PO1ALYc8kcKE%3D&t=4d5b0474&ps=13740610&shp=81f88b70&shcp=9b759fb9&idc=useast5&ftpl=1", "https://p19-common-sign.tiktokcdn-us.com/tos-no1a-i-photomode-no/9a5db9e6350a46db830f619db1e97454~tplv-photomode-image.jpeg?dr=9616&x-expires=1771423200&x-signature=vbSjZg%2Bw2FQ7rMUbm8VwW3NQtGU%3D&t=4d5b0474&ps=13740610&shp=81f88b70&shcp=9b759fb9&idc=useast5&ftpl=1"]}, "imageWidth": 1080, "imageHeight": 2030}, "shareCover": {"imageURL": {"urlList": ["https://p16-common-sign.tiktokcdn-us.com/tos-no1a-i-photomode-no/9a5db9e6350a46db830f619db1e97454~tplv-photomode-image.jpeg?dr=9616&x-expires=1771423200&x-signature=CGUDofojgnfF%2Fs3PO1ALYc8kcKE%3D&t=4d5b0474&ps=13740610&shp=81f88b70&shcp=9b759fb9&idc=useast5&ftpl=1", "https://p19-common-sign.tiktokcdn-us.com/tos-no1a-i-photomode-no/9a5db9e6350a46db830f619db1e97454~tplv-photomode-image.jpeg?dr=9616&x-expires=1771423200&x-signature=vbSjZg%2Bw2FQ7rMUbm8VwW3NQtGU%3D&t=4d5b0474&ps=13740610&shp=81f88b70&shcp=9b759fb9&idc=useast5&ftpl=1"]}, "imageWidth": 1080, "imageHeight": 2030}, "title": ""}, "locationCreated": "IT", "suggestedWords": [], "contents": [], "collected": false, "channelTags": [], "item_control": {"can_repost": true}, "IsAigc": false, "AIGCDescription": "", "backendSourceEventTracking": "", "CategoryType": 120, "textLanguage": "un", "textTranslatable": false, "titleLanguage": "un", "titleTranslatable": false, "authorStatsV2": {"followerCount": "8034", "followingCount": "6320", "heart": "218800", "heartCount": "218800", "videoCount": "15000", "diggCount": "230900", "friendCount": "0"}, "isReviewing": false, "creatorAIComment": {"hasAITopic": false, "categoryList": [], "eligibleVideo": false, "notEligibleReason": 101}}}, "shareMeta": {"title": "napoletana on TikTok", "desc": "napoletana's short video with \u266c suono originale"}, "statusCode": 0, "statusMsg": ""}